Workbook

Sheet Cover Page
B2: NVIDIA DCF Valuation Using Financial Statements
B4: Date | C4: November 12, 2025
B5: Prepared By | C5: Braeden Tuazon
B6: Purpose | C6: This model estimates the intrinsic value of NVIDIA using a Discounted Cash Flow (DCF) approach, based on real financial statement data (income statement, balance sheet, and cash flows) and market inputs such as WACC, beta, and risk-free rate.
B7: Data Sources | C7: NVIDIA 10-Q and 10-K reports, Yahoo Finance, AlphaSpread, Bloomberg, Morningstar, GuruFocus, Finbox, FactSet, Reuters, U.S. Treasury, and self-calculated estimates where applicable.
B9: Key Valuation Results | C9: Values
B10: Market Share Price | C10: ='DCF Valuation'!J5 -> 193.16
B11: DCF Implied Share Price | C11: ='DCF Valuation'!J4 -> 739.15195
B12: Upside Potential | C12: ='DCF Valuation'!J6 -> 2.8266305
B13: WACC | C13: =WACC!F21 -> 0.10255877
B14: Terminal Growth Rate | C14: 3.5%
B15: Valuation Date | C15: November 12, 2025
B17: Key Assumptions Table | C17: Values
B18: Cost of Equity | C18: =WACC!F11 -> 0.1027
B19: Beta | C19: 1.2
B20: Risk-Free Rate | C20: =WACC!F12 -> 0.0415
B21: Market Risk Premium | C21: =WACC!F14 -> 0.051
B22: Cost of Debt | C22: =WACC!F18 -> 0.039
B23: Tax Rate | C23: =WACC!F19 -> 0.17
B25: Workbook Tabs Overview | C25: Description
B26: Revenue Streams | C26: Breakdown of NVIDIA's product/service revenue over time
B27: Income Statement | C27: Quarterly income performance including revenue, expenses, and net income
B28: Balance Sheet | C28: Snapshot of assets, liabilities, and equity over time
B29: Cash Flow Statement | C29: Cash inflows/outflows from operations, investing and financing activities
B30: Working Capital | C30: Detailed calculation of current assets and liabilities for forecasting purposes
B31: Debt | C31: NVIDIA's debt levels, interest expense, and cost of debt inputs
B32: Fixed Assets | C32: Capital expenditures, depreciation, and asset base tracking
B33: WACC | C33: Weighted Average Cost of Capital calculation based on market inputs
B34: DCF Valuation | C34: Free Cash Flow forecast, terminal value, and intrinsic value estimation
B36: Disclaimer: For academic use only. Not intended as financial or investment advice.

Sheet Revenue Streams
A2: Revenue Streams
A4: ($ in millions) | B4: Q1 2020 | C4: Q2 2020 | D4: Q3 2020 | E4: Q4 2020 | F4: Q1 2021 | G4: Q2 2021 | H4: Q3 2021 | I4: Q4 2021 | J4: Q1 2022 | K4: Q2 2022 | L4: Q3 2022 | M4: Q4 2022 | N4: Q1 2023 | O4: Q2 2023 | P4: Q3 2023 | Q4: Q4 2023 | R4: Q1 2024 | S4: Q2 2024 | T4: Q3 2024 | U4: Q4 2024
A5: Data Center | B5: =1/3*B25+2/3*C25 -> 1083.3333 | C5: =1/3*C25+2/3*D25 -> 1548.3333 | D5: =1/3*D25+2/3*E25 -> 1850.6667 | E5: =1/3*E25+2/3*F25 -> 1902 | F5: =1/3*F25+2/3*G25 -> 1999.6667 | G5: =1/3*G25+2/3*H25 -> 2260 | H5: =1/3*H25+2/3*I25 -> 2746 | I5: =1/3*I25+2/3*J25 -> 3154 | ... T5: =1/3*T25+2/3*U25 -> 29303.667 | U5: =1/3*U25+2/3*W22 -> 10266.667
A6: Data Center | B6: =B5/B$20 -> 0.35078251 | C6: =C5/C$20 -> 0.42961524 | D6: =D5/D$20 -> 0.41687941 | E6: =E5/E$20 -> 0.38732012 | F6: =F5/F$20 -> 0.3674732 | G6: =G5/G$20 -> 0.36305221 | H6: =H5/H$20 -> 0.39772124 | I6: =I5/I$20 -> 0.42261825 | ... U6: =U5/U$20 -> 0.8779431
A8: Gaming | B8: =1/3*B29+2/3*C29 -> 1389.6667 | C8: =1/3*C29+2/3*D29 -> 1549 | D8: =1/3*D29+2/3*E29 -> 2065.3333 | E8: =1/3*E29+2/3*F29 -> 2420.3333 | F8: =1/3*F29+2/3*G29 -> 2671.6667 | G8: =1/3*G29+2/3*H29 -> 2960.6667 | H8: =1/3*H29+2/3*I29 -> 3167.6667 | I8: =1/3*I29+2/3*J29 -> 3353.6667 | ... T8: =1/3*T29+2/3*U29 -> 3165 | U8: =1/3*U29+2/3*W26 -> 1100
A9: Gaming | B9: =B8/B$20 -> 0.44997302 | C9: =C8/C$20 -> 0.42980022 | D9: =D8/D$20 -> 0.46523502 | E9: =E8/E$20 -> 0.49287266 | F9: =F8/F$20 -> 0.49096478 | G9: =G8/G$20 -> 0.4756091 | H9: =H8/H$20 -> 0.45879399 | I9: =I8/I$20 -> 0.44937246 | ... U9: =U8/U$20 -> 0.094065333
A11: Professional Visualization | B11: =1/3*B33+2/3*C33 -> 315 | C11: =1/3*C33+2/3*D33 -> 237.66667 | D11: =1/3*D33+2/3*E33 -> 225 | E11: =1/3*E33+2/3*F33 -> 283.33333 | F11: =1/3*F33+2/3*G33 -> 350.33333 | G11: =1/3*G33+2/3*H33 -> 470 | H11: =1/3*H33+2/3*I33 -> 557.66667 | I11: =1/3*I33+2/3*J33 -> 621 | ... T11: =1/3*T33+2/3*U33 -> 475.33333 | U11: =1/3*U33+2/3*W30 -> 162
A12: Professional Visualization | B12: =B11/B$20 -> 0.10199676 | C12: =C11/C$20 -> 0.065945246 | D12: =D11/D$20 -> 0.050683286 | E12: =E11/E$20 -> 0.057697529 | F12: =F11/F$20 -> 0.064379786 | G12: =G11/G$20 -> 0.075502008 | H12: =H11/H$20 -> 0.080770531 | I12: =I11/I$20 -> 0.083210505 | ... U12: =U11/U$20 -> 0.013853258
A14: Auto | B14: =1/3*B37+2/3*C37 -> 157.66667 | C14: =1/3*C37+2/3*D37 -> 125.66667 | D14: =1/3*D37+2/3*E37 -> 120.33333 | E14: =1/3*E37+2/3*F37 -> 138.33333 | F14: =1/3*F37+2/3*G37 -> 151 | G14: =1/3*G37+2/3*H37 -> 152.66667 | H14: =1/3*H37+2/3*I37 -> 140.66667 | I14: =1/3*I37+2/3*J37 -> 128.33333 | ... T14: =1/3*T37+2/3*U37 -> 414.66667 | U14: =1/3*U37+2/3*W34 -> 149.66667
A15: Auto | B15: =B14/B$20 -> 0.051052348 | C15: =C14/C$20 -> 0.034868664 | D15: =D14/D$20 -> 0.027106172 | E15: =E14/E$20 -> 0.02816997 | F15: =F14/F$20 -> 0.027748851 | G15: =G14/G$20 -> 0.024524766 | H15: =H14/H$20 -> 0.020373678 | I15: =I14/I$20 -> 0.017195944 | ... U15: =U14/U$20 -> 0.012798586
A17: OEM & Other | B17: =1/3*B41+2/3*C41 -> 142.66667 | C17: =1/3*C41+2/3*D41 -> 143.33333 | D17: =1/3*D41+2/3*E41 -> 178 | E17: =1/3*E41+2/3*F41 -> 166.66667 | F17: =1/3*F41+2/3*G41 -> 269 | G17: =1/3*G41+2/3*H41 -> 381.66667 | H17: =1/3*H41+2/3*I41 -> 292.33333 | I17: =1/3*I41+2/3*J41 -> 206 | ... T17: =1/3*T41+2/3*U41 -> 42.666667 | U17: =1/3*U41+2/3*W38 -> 15.666667
A18: OEM & Other | B18: =B17/B$20 -> 0.046195359 | C18: =C17/C$20 -> 0.039770625 | D18: =D17/D$20 -> 0.040096111 | E18: =E17/E$20 -> 0.033939723 | F18: =F17/F$20 -> 0.049433384 | G18: =G17/G$20 -> 0.061311914 | H18: =H17/H$20 -> 0.042340559 | I18: =I17/I$20 -> 0.027602841 | ... U18: =U17/U$20 -> 0.0013397184
A20: Total | B20: =SUM(B5,B8,B11,B14,B17) -> 3088.3333 | C20: =SUM(C5,C8,C11,C14,C17) -> 3604 | D20: =SUM(D5,D8,D11,D14,D17) -> 4439.3333 | E20: =SUM(E5,E8,E11,E14,E17) -> 4910.6667 | F20: =SUM(F5,F8,F11,F14,F17) -> 5441.6667 | G20: =SUM(G5,G8,G11,G14,G17) -> 6225 | H20: =SUM(H5,H8,H11,H14,H17) -> 6904.3333 | I20: =SUM(I5,I8,I11,I14,I17) -> 7463 | ... U20: =SUM(U5,U8,U11,U14,U17) -> 11694
A22: Revenue Streams
A24: ($ in millions) | B24: Q4 2020 | C24: Q1 2021 | D24: Q2 2021 | E24: Q3 2021 | F24: Q4 2021 | G24: Q1 2022 | H24: Q2 2022 | I24: Q3 2022 | J24: Q4 2022 | K24: Q1 2023 | L24: Q2 2023 | M24: Q3 2023 | N24: Q4 2023 | O24: Q1 2024 | P24: Q2 2024 | Q24: Q3 2024 | R24: Q4 2024 | S24: Q1 2025 | T24: Q2 2025 | U24: Q3 2025
A25: Data Center | B25: 968 | C25: 1141 | D25: 1752 | E25: 1900 | F25: 1903 | G25: 2048 | H25: 2366 | I25: 2936 | J25: 3263 | K25: 3750 | L25: 3806 | M25: 3833 | N25: 3616 | O25: 4284 | P25: 10323 | Q25: 14514 | R25: 18404 | S25: 22563 | T25: 26311 | U25: 30800
A26: % change | C26: =C25/B25-1 -> 0.17871901 | D26: =D25/C25-1 -> 0.53549518 | E26: =E25/D25-1 -> 0.084474886 | F26: =F25/E25-1 -> 0.0015789474 | G26: =G25/F25-1 -> 0.076195481 | H26: =H25/G25-1 -> 0.15527344 | I26: =I25/H25-1 -> 0.24091293 | J26: =J25/I25-1 -> 0.11137602 | ... U26: =U25/T25-1 -> 0.17061305
A27: % of total | B27: =B25/B$45 -> 0.31175523 | C27: =C25/C$45 -> 0.37045455 | D27: =D25/D$45 -> 0.45318158 | E27: =E25/E$45 -> 0.40203132 | F27: =F25/F$45 -> 0.38037178 | G27: =G25/G$45 -> 0.36177354 | H27: =H25/H$45 -> 0.36360842 | I27: =I25/I$45 -> 0.41334647 | ... U27: =U25/U$45 -> 0.8779431
A29: Gaming | B29: 1491 | C29: 1339 | D29: 1654 | E29: 2271 | F29: 2495 | G29: 2760 | H29: 3061 | I29: 3221 | J29: 3420 | K29: 3620 | L29: 2042 | M29: 1574 | N29: 1831 | O29: 2240 | P29: 2486 | Q29: 2856 | R29: 2865 | S29: 2649 | T29: 2895 | U29: 3300
A30: % change | C30: =C29/B29-1 -> -0.101945 | D30: =D29/C29-1 -> 0.23525019 | E30: =E29/D29-1 -> 0.37303507 | F30: =F29/E29-1 -> 0.098634963 | G30: =G29/F29-1 -> 0.10621242 | H30: =H29/G29-1 -> 0.10905797 | I30: =I29/H29-1 -> 0.0522705 | J30: =J29/I29-1 -> 0.061782055 | ... U30: =U29/T29-1 -> 0.13989637
A31: % of total | B31: =B29/B$45 -> 0.48019324 | C31: =C29/C$45 -> 0.43474026 | D31: =D29/D$45 -> 0.42783238 | E31: =E29/E$45 -> 0.48053322 | F31: =F29/F$45 -> 0.49870078 | G31: =G29/G$45 -> 0.48754637 | H31: =H29/H$45 -> 0.47041647 | I31: =I29/I$45 -> 0.45347036 | ... U31: =U29/U$45 -> 0.094065333
A33: Professional Visualization | B33: 331 | C33: 307 | D33: 203 | E33: 236 | F33: 307 | G33: 372 | H33: 519 | I33: 577 | J33: 643 | K33: 622 | L33: 496 | M33: 200 | N33: 226 | O33: 295 | P33: 379 | Q33: 416 | R33: 463 | S33: 427 | T33: 454 | U33: 486
A34: % change | C34: =C33/B33-1 -> -0.072507553 | D34: =D33/C33-1 -> -0.33876221 | E34: =E33/D33-1 -> 0.16256158 | F34: =F33/E33-1 -> 0.30084746 | G34: =G33/F33-1 -> 0.21172638 | H34: =H33/G33-1 -> 0.39516129 | I34: =I33/H33-1 -> 0.11175337 | J34: =J33/I33-1 -> 0.11438475 | ... U34: =U33/T33-1 -> 0.070484581
A35: % of total | B35: =B33/B$45 -> 0.10660225 | C35: =C33/C$45 -> 0.099675325 | D35: =D33/D$45 -> 0.052509053 | E35: =E33/E$45 -> 0.049936521 | F35: =F33/F$45 -> 0.061363182 | G35: =G33/G$45 -> 0.065712772 | H35: =H33/H$45 -> 0.079760258 | I35: =I33/I$45 -> 0.081233282 | ... U35: =U33/U$45 -> 0.013853258
A37: Auto | B37: 163 | C37: 155 | D37: 111 | E37: 125 | F37: 145 | G37: 154 | H37: 152 | I37: 135 | J37: 125 | K37: 138 | L37: 220 | M37: 251 | N37: 294 | O37: 296 | P37: 253 | Q37: 261 | R37: 281 | S37: 329 | T37: 346 | U37: 449
A38: % change | C38: =C37/B37-1 -> -0.049079755 | D38: =D37/C37-1 -> -0.28387097 | E38: =E37/D37-1 -> 0.12612613 | F38: =F37/E37-1 -> 0.16 | G38: =G37/F37-1 -> 0.062068966 | H38: =H37/G37-1 -> -0.012987013 | I38: =I37/H37-1 -> -0.11184211 | J38: =J37/I37-1 -> -0.074074074 | ... U38: =U37/T37-1 -> 0.29768786
A39: % of total | B39: =B37/B$45 -> 0.052495974 | C39: =C37/C$45 -> 0.050324675 | D39: =D37/D$45 -> 0.028711847 | E39: =E37/E$45 -> 0.026449429 | F39: =F37/F$45 -> 0.02898261 | G39: =G37/G$45 -> 0.027203674 | H39: =H37/H$45 -> 0.023359459 | I39: =I37/I$45 -> 0.019006054 | ... U39: =U37/U$45 -> 0.012798586
A41: OEM & Other | B41: 152 | C41: 138 | D41: 146 | E41: 194 | F41: 153 | G41: 327 | H41: 409 | I41: 234 | J41: 192 | K41: 158 | L41: 140 | M41: 73 | N41: 84 | O41: 77 | P41: 66 | Q41: 73 | R41: 90 | S41: 76 | T41: 34 | U41: 47
A42: % change | C42: =C41/B41-1 -> -0.092105263 | D42: =D41/C41-1 -> 0.057971014 | E42: =E41/D41-1 -> 0.32876712 | F42: =F41/E41-1 -> -0.21134021 | G42: =G41/F41-1 -> 1.1372549 | H42: =H41/G41-1 -> 0.25076453 | I42: =I41/H41-1 -> -0.42787286 | J42: =J41/I41-1 -> -0.17948718 | ... U42: =U41/T41-1 -> 0.38235294
A43: % of total | B43: =B41/B$45 -> 0.048953301 | C43: =C41/C$45 -> 0.044805195 | D43: =D41/D$45 -> 0.037765132 | E43: =E41/E$45 -> 0.041049513 | F43: =F41/F$45 -> 0.030581651 | G43: =G41/G$45 -> 0.057763646 | H43: =H41/H$45 -> 0.062855387 | I43: =I41/I$45 -> 0.032943827 | ... U43: =U41/U$45 -> 0.0013397184
A45: Total | B45: =SUM(B25,B29,B33,B37,B41) -> 3105 | C45: =SUM(C25,C29,C33,C37,C41) -> 3080 | D45: =SUM(D25,D29,D33,D37,D41) -> 3866 | E45: =SUM(E25,E29,E33,E37,E41) -> 4726 | F45: =SUM(F25,F29,F33,F37,F41) -> 5003 | G45: =SUM(G25,G29,G33,G37,G41) -> 5661 | H45: =SUM(H25,H29,H33,H37,H41) -> 6507 | I45: =SUM(I25,I29,I33,I37,I41) -> 7103 | ... U45: =SUM(U25,U29,U33,U37,U41) -> 35082
A46: % change | C46: =C45/B45-1 -> -0.0080515298 | D46: =D45/C45-1 -> 0.25519481 | E46: =E45/D45-1 -> 0.22245215 | F46: =F45/E45-1 -> 0.058611934 | G46: =G45/F45-1 -> 0.13152109 | H46: =H45/G45-1 -> 0.14944356 | I46: =I45/H45-1 -> 0.091593668 | J46: =J45/I45-1 -> 0.076024215 | ... U46: =U45/T45-1 -> 0.16784288
A48: OEM & Other | B48: Original Equipment Manufacturers

Sheet Income Statement
A2: Income Statement
A3: All figures in millions USD (except per-share amounts)
A6: Fiscal Year | B6: Q4 2020 | C6: Q1 2021 | D6: Q2 2021 | E6: Q3 2021 | F6: Q4 2021 | G6: Q1 2022 | H6: Q2 2022 | I6: Q3 2022 | J6: Q4 2022 | K6: Q1 2023 | L6: Q2 2023 | M6: Q3 2023 | N6: Q4 2023 | O6: Q1 2024 | P6: Q2 2024 | Q6: Q3 2024 | R6: Q4 2024 | S6: Q1 2025 | T6: Q2 2025
A7: Quarterly Date | B7: 44227 | C7: 44318 | D7: 44409 | E7: 44500 | F7: 44591 | G7: 44682 | H7: 44773 | I7: 44864 | J7: 44955 | K7: 45046 | L7: 45137 | M7: 45228 | N7: 45319 | O7: 45410 | P7: 45501 | Q7: 45592 | R7: 45683 | S7: 45774 | T7: 45865
A9: Revenue | B9: 5003 | C9: 5,661 | D9: 6,507 | E9: 7103 | F9: 7643 | G9: 8288 | H9: 6,704 | I9: 5,931 | J9: 6051 | K9: 7192 | L9: 13507 | M9: 18120 | N9: 22103 | O9: 26044 | P9: 30040 | Q9: 35082 | R9: 39331 | S9: 44062 | T9: 46743
A10: Cost of revenue | B10: 1846 | C10: 2,032 | D10: 2,292 | E10: 2,472 | F10: 2643 | G10: 2857 | H10: 3,789 | I10: 2,754 | J10: 2218 | K10: 2544 | L10: 4045 | M10: 4720 | N10: 5312 | O10: 5638 | P10: 7466 | Q10: 8926 | R10: 10608 | S10: 17394 | T10: 12890
A11: Gross profit | B11: 3157 | C11: 3,629 | D11: 4,215 | E11: 4,631 | F11: 5000 | G11: 5431 | H11: 2,915 | I11: 3,177 | J11: 3833 | K11: 4648 | L11: 9462 | M11: 13400 | N11: 16791 | O11: 20406 | P11: 22574 | Q11: 26156 | R11: 28723 | S11: 26668 | T11: 33853
A13: Operating Expenses
A14: Research and development | B14: 1145 | C14: 1,153 | D14: 1,245 | E14: 1,403 | F14: 1467 | G14: 1618 | H14: 1,824 | I14: 1,945 | J14: 1952 | K14: 1875 | L14: 2040 | M14: 2294 | N14: 2466 | O14: 2720 | P14: 3090 | Q14: 3390 | R14: 3714 | S14: 3989 | T14: 4291
A15: Sales, general and administrative | B15: 505 | C15: 520 | D15: 526 | E15: 557 | F15: 563 | G15: 592 | H15: 592 | I15: 631 | J15: 625 | K15: 633 | L15: 622 | M15: 689 | N15: 710 | O15: 777 | P15: 842 | Q15: 897 | R15: 975 | S15: 1041 | T15: 1122
A16: Acquisition termination cost | B16: — | C16: — | D16: — | E16: — | F16: — | G16: 1353 | H16: — | I16: — | J16: — | K16: — | L16: — | M16: — | N16: — | O16: — | P16: — | Q16: — | R16: — | S16: — | T16: —
A17: Total operating expenses | B17: 1650 | C17: 1,673 | D17: 1,771 | E17: 1,960 | F17: 2030 | G17: 3563 | H17: 2,416 | I17: 2,576 | J17: 2577 | K17: 2508 | L17: 2662 | M17: 2983 | N17: 3176 | O17: 3497 | P17: 3932 | Q17: 4287 | R17: 4689 | S17: 5030 | T17: 5413
A19: Operating income | B19: 1507 | C19: 1,956 | D19: 2,444 | E19: 2,671 | F19: 2970 | G19: 1868 | H19: 499 | I19: 601 | J19: 1256 | K19: 2140 | L19: 6800 | M19: 10417 | N19: 13615 | O19: 16909 | P19: 18642 | Q19: 21869 | R19: 24034 | S19: 21638 | T19: 28440
A20: Interest income | B20: 7 | C20: 6 | D20: 6 | E20: 7 | F20: 10 | G20: 18 | H20: 46 | I20: 88 | J20: 115 | K20: 150 | L20: 187 | M20: 234 | N20: 295 | O20: 359 | P20: 444 | Q20: 472 | R20: 511 | S20: 515 | T20: 592
A21: Interest expense | B21: -52 | C21: -53 | D21: (60) | E21: (62) | F21: -61 | G21: -68 | H21: (65) | I21: (65) | J21: -64 | K21: -66 | L21: -65 | M21: -63 | N21: -63 | O21: -64 | P21: -61 | Q21: -61 | R21: -61 | S21: -63 | T21: -62
A22: Other income (expense), net | B22: 10 | C22: 135 | D22: 4 | E22: 22 | F22: -54 | G22: -13 | H22: (5) | I22: (11) | J22: -19 | K22: -15 | L22: 59 | M22: -66 | N22: 259 | O22: 75 | P22: 189 | Q22: 36 | R22: 733 | S22: -180 | T22: 2236
A23: Total other income (expense), net | B23: -36 | C23: 88 | D23: (50) | E23: (33) | F23: -105 | G23: -63 | H23: (24) | I23: 12 | J23: 32 | K23: 69 | L23: 181 | M23: 105 | N23: 491 | O23: 370 | P23: 249 | Q23: 447 | R23: 1183 | S23: 272 | T23: 2766
A25: Income before income tax | B25: 1471 | C25: 2,044 | D25: 2,394 | E25: 2,638 | F25: 2865 | G25: 1805 | H25: 475 | I25: 613 | J25: 1288 | K25: 2209 | L25: 6981 | M25: 10522 | N25: 14106 | O25: 17279 | P25: 19214 | Q25: 22316 | R25: 25217 | S25: 21910 | T25: 31206
A26: Income tax expense | B26: 14 | C26: 132 | D26: 20 | E26: 174 | F26: -137 | G26: 187 | H26: (181) | I26: (67) | J26: -126 | K26: 166 | L26: 793 | M26: 1279 | N26: 1820 | O26: 2398 | P26: 2615 | Q26: 3007 | R26: 3126 | S26: 3135 | T26: 4784
A27: Net income | B27: 1457 | C27: 1,912 | D27: 2,374 | E27: 2,464 | F27: 3002 | G27: 1618 | H27: 656 | I27: 680 | J27: 1414 | K27: 2043 | L27: 6188 | M27: 9243 | N27: 12286 | O27: 14881 | P27: 16599 | Q27: 19309 | R27: 22091 | S27: 18775 | T27: 26422
A29: Net income per share:
A30: Basic | B30: 2.36 | C30: 0.77 | D30: 0.95 | E30: 0.99 | F30: 1.2 | G30: 0.65 | H30: 0.26 | I30: 0.27 | J30: 0.58 | K30: 0.83 | L30: 0.25 | M30: 0.37 | N30: 4.97 | O30: 0.6 | P30: 0.68 | Q30: 0.79 | R30: 0.9 | S30: 0.77 | T30: 1.08
A31: Diluted | B31: 2.32 | C31: 0.76 | D31: 0.94 | E31: 0.97 | F31: 1.18 | G31: 0.64 | H31: 0.26 | I31: 0.27 | J31: 0.57 | K31: 0.82 | L31: 0.25 | M31: 0.37 | N31: 4.92 | O31: 0.6 | P31: 0.67 | Q31: 0.78 | R31: 0.89 | S31: 0.76 | T31: 1.08
A33: Weighted average shares used in per share:
A34: Basic | B34: 617 | C34: 2,484 | D34: 2,493 | E34: 2,499 | F34: 2,496 | G34: 2506 | H34: 2,495 | I34: 2483 | J34: 2,487 | K34: 2470 | L34: 2473 | M34: 2468 | N34: 2469 | O34: 2462 | P34: 2458 | Q34: 2453 | R34: 2449 | S34: 244 | T34: 2437
A35: Diluted | B35: 628 | C35: 2,528 | D35: 2,532 | E35: 2,538 | F35: 2,535 | G35: 2537 | H35: 2,516 | I35: 2499 | J35: 2,507 | K35: 2490 | L35: 2499 | M35: 2494 | N35: 2494 | O35: 2489 | P35: 2485 | Q35: 2477 | R35: 2471 | S35: 2461 | T35: 2453

Sheet Balance Sheet
A2: Balance Sheet
A3: All figures in millions USD (except per-share amounts)
A6: Fiscal Year | B6: Q4 2020 | C6: Q1 2021 | D6: Q2 2021 | E6: Q3 2021 | F6: Q4 2021 | G6: Q1 2022 | H6: Q2 2022 | I6: Q3 2022 | J6: Q4 2022 | K6: Q1 2023 | L6: Q2 2023 | M6: Q3 2023 | N6: Q4 2023 | O6: Q1 2024 | P6: Q2 2024 | Q6: Q3 2024 | R6: Q4 2024 | S6: Q1 2025 | T6: Q2 2025
A7: Quarterly Date | B7: 44227 | C7: 44318 | D7: 44409 | E7: 44500 | F7: 44591 | G7: 44682 | H7: 44773 | I7: 44864 | J7: 44955 | K7: 45046 | L7: 45137 | M7: 45228 | N7: 45319 | O7: 45410 | P7: 45501 | Q7: 45592 | R7: 45683 | S7: 45774 | T7: 45865
A9: Assets
A10: Current assets:
A11: Cash and cash equivalents | B11: 847 | C11: 978 | D11: 5628 | E11: 1288 | F11: 1990 | G11: 3887 | H11: 3013 | I11: 2800 | J11: 3,389 | K11: 5079 | L11: 5,783 | M11: 5519 | N11: 7280 | O11: 7587 | P11: 8571 | Q11: 9107 | R11: 8589 | S11: 15234 | T11: 11639
A12: Marketable securities | B12: 10714 | C12: 11689 | D12: 14026 | E12: 18010 | F12: 19218 | G12: 16451 | H12: 14024 | I12: 10343 | J12: 9,907 | K12: 10241 | L12: 10,240 | M12: 12762 | N12: 18704 | O12: 23851 | P12: 26229 | Q12: 29380 | R12: 34621 | S12: 38457 | T12: 45152
A13: Accounts receivable, net | B13: 2429 | C13: 3024 | D13: 3586 | E13: 3954 | F13: 4650 | G13: 5438 | H13: 5317 | I13: 4908 | J13: 3,827 | K13: 4080 | L13: 7,066 | M13: 8309 | N13: 9999 | O13: 12365 | P13: 14132 | Q13: 17693 | R13: 23065 | S13: 22132 | T13: 27808
A14: Inventories | B14: 1826 | C14: 1992 | D14: 2114 | E14: 2233 | F14: 2605 | G14: 3163 | H14: 3889 | I14: 4454 | J14: 5,159 | K14: 4611 | L14: 4,319 | M14: 4779 | N14: 5282 | O14: 5864 | P14: 6675 | Q14: 7654 | R14: 10080 | S14: 11333 | T14: 14962
A15: Prepaid expenses and other current assets | B15: 239 | C15: 444 | D15: 452 | E15: 321 | F15: 366 | G15: 636 | H15: 1175 | I15: 718 | J15: 791 | K15: 872 | L15: 1,389 | M15: 1289 | N15: 3080 | O15: 4062 | P15: 4026 | Q15: 3806 | R15: 3771 | S15: 2779 | T15: 2658
A16: Total current assets | B16: 16055 | C16: 18127 | D16: 25806 | E16: 25806 | F16: 28829 | G16: 29575 | H16: 27418 | I16: 23223 | J16: 23,073 | K16: 24883 | L16: 28,797 | M16: 32658 | N16: 44345 | O16: 53729 | P16: 59633 | Q16: 67640 | R16: 80126 | S16: 89935 | T16: 102219
A17: Property and equipment, net | B17: 2149 | C17: 2268 | D17: 2364 | E17: 2509 | F17: 2778 | G17: 2916 | H17: 3233 | I17: 3774 | J17: 3,807 | K17: 3740 | L17: 3,799 | M17: 3844 | N17: 3914 | O17: 4006 | P17: 4885 | Q17: 5343 | R17: 6283 | S17: 7136 | T17: 9141
A18: Operating lease assets | B18: 707 | C18: 727 | D18: 801 | E18: 830 | F18: 829 | G18: 856 | H18: 852 | I18: 927 | J18: 1,038 | K18: 1094 | L18: 1,235 | M18: 1316 | N18: 1346 | O18: 1532 | P18: 1556 | Q18: 1755 | R18: 1793 | S18: 1810 | T18: 2084
A19: Goodwill | B19: 4193 | C19: 4193 | D19: 4193 | E19: 4302 | F19: 4349 | G19: 4365 | H19: 4372 | I19: 4372 | J19: 4,372 | K19: 4430 | L19: 4,430 | M19: 4430 | N19: 4430 | O19: 4453 | P19: 4622 | Q19: 4724 | R19: 5188 | S19: 5498 | T19: 5755
A20: Intangible assets, net | B20: 2737 | C20: 2613 | D20: 2478 | E20: 2454 | F20: 2339 | G20: 2211 | H20: 2036 | I20: 1850 | J20: 1,676 | K20: 1541 | L20: 1,395 | M20: 1251 | N20: 1112 | O20: 986 | P20: 952 | Q20: 838 | R20: 807 | S20: 769 | T20: 755
A21: Deferred income tax assets | B21: 806 | C21: 778 | D21: 958 | E21: 970 | F21: 1222 | G21: 1784 | H21: 2225 | I21: 2762 | J21: 3,396 | K21: 4568 | L21: 5,398 | M21: 5982 | N21: 6081 | O21: 7798 | P21: 9578 | Q21: 10276 | R21: 10979 | S21: 13318 | T21: 13570
A22: Other assets | B22: 2144 | C22: 2090 | D22: 2050 | E22: 3761 | F22: 3841 | G22: 3505 | H22: 3340 | I22: 3580 | J22: 3,820 | K22: 4204 | L22: 4,501 | M22: 4667 | N22: 4500 | O22: 4568 | P22: 4001 | Q22: 5437 | R22: 6425 | S22: 6788 | T22: 7216
A23: Total assets | B23: 28791 | C23: 30796 | D23: 38650 | E23: 40632 | F23: 44187 | G23: 45212 | H23: 43476 | I23: 40488 | J23: 41,182 | K23: 44460 | L23: 49,555 | M23: 54148 | N23: 65728 | O23: 77072 | P23: 85227 | Q23: 96013 | R23: 111601 | S23: 125254 | T23: 140740
A25: Liabilities and Shareholders' Equity
A26: Current liabilities:
A27: Accounts payable | B27: 1201 | C27: 1218 | D27: 1474 | E27: 1664 | F27: 1783 | G27: 1999 | H27: 2421 | I27: 1491 | J27: 1,193 | K27: 1141 | L27: 1,929 | M27: 2380 | N27: 2699 | O27: 2715 | P27: 3680 | Q27: 5353 | R27: 6310 | S27: 7331 | T27: 9064
A28: Accrued and other current liabilities | B28: 1725 | C28: 1787 | D28: 1974 | E28: 1948 | F28: 2552 | G28: 3563 | H28: 3903 | I28: 4115 | J28: 4,120 | K28: 4869 | L28: 7,156 | M28: 5472 | N28: 6682 | O28: 11258 | P28: 10289 | Q28: 11126 | R28: 11737 | S28: 19211 | T28: 15193
A29: Short-term debt | B29: 999 | C29: 999 | D29: 1000 | E29: 0 | F29: 0 | G29: 0 | H29: 1249 | I29: 1249 | J29: 1,250 | K29: 1250 | L29: 1,249 | M29: 1249 | N29: 1250 | O29: 1250 | P29: 0 | Q29: 0 | R29: 0 | S29: 0 | T29: 0
A30: Total current liabilities | B30: 3925 | C30: 4004 | D30: 4448 | E30: 3612 | F30: 4335 | G30: 5562 | H30: 7573 | I30: 6855 | J30: 6,563 | K30: 7260 | L30: 10,334 | M30: 9101 | N30: 10631 | O30: 15223 | P30: 13969 | Q30: 16479 | R30: 18047 | S30: 26542 | T30: 24257
A31: Long-term debt | B31: 5964 | C31: 5964 | D31: 10943 | E31: 10944 | F31: 10946 | G31: 10947 | H31: 9700 | I31: 9701 | J31: 9,703 | K31: 9704 | L31: 8,456 | M31: 8457 | N31: 8459 | O31: 8460 | P31: 8461 | Q31: 8462 | R31: 8463 | S31: 8464 | T31: 8466
A32: Long-term operating lease liabilities | B32: 634 | C32: 640 | D32: 716 | E32: 743 | F32: 741 | G32: 752 | H32: 743 | I32: 798 | J32: 902 | K32: 939 | L32: 1,041 | M32: 1091 | N32: 1119 | O32: 1281 | P32: 1304 | Q32: 1490 | R32: 1519 | S32: 1521 | T32: 1831
A33: Other long-term liabilities | B33: 1375 | C33: 1414 | D33: 1396 | E33: 1535 | F33: 1553 | G33: 1631 | H33: 1609 | I33: 1785 | J33: 1,913 | K33: 2037 | L33: 2,223 | M33: 2234 | N33: 2541 | O33: 2966 | P33: 3336 | Q33: 3683 | R33: 4245 | S33: 4884 | T33: 6055
A34: Total liabilities | B34: 11898 | C34: 12022 | D34: 17503 | E34: 16834 | F34: 17575 | G34: 18892 | H34: 19625 | I34: 19139 | J34: 19,081 | K34: 19940 | L34: 22,054 | M34: 20883 | N34: 22750 | O34: 27930 | P34: 27070 | Q34: 30114 | R34: 32274 | S34: 41411 | T34: 40609
A36: Commitments and Contingencies
A37: Shareholders’ equity
A38: Preferred stock | B38: — | C38: — | D38: — | E38: — | F38: — | G38: — | H38: — | I38: — | J38: — | K38: — | L38: — | M38: — | N38: — | O38: — | P38: — | Q38: — | R38: — | S38: — | T38: —
A39: Common stock | B39: 3 | C39: 1 | D39: 3 | E39: 3 | F39: 3 | G39: 3 | H39: 2 | I39: 2 | J39: 2 | K39: 2 | L39: 2 | M39: 2 | N39: 2
A40: Additional paid-in capital | B40: 8719 | C40: 9280 | D40: 9745 | E40: 10465 | F40: 10385 | G40: 10623 | H40: 10968 | I40: 11565 | J40: 11,971 | K40: 12453 | L40: 12,629 | M40: 12991 | N40: 13132
A41: Accumulated other comprehensive loss | B41: 19 | C41: 14 | D41: 8 | E41: 9 | F41: -11 | G41: -64 | H41: -90 | I41: -123 | J41: (43) | K41: -50 | L41: (51) | M41: -88 | N41: 27
A42: Retained earnings | B42: 18908 | C42: 20721 | D42: 22995 | E42: 25359 | F42: 16235 | G42: 15758 | H42: 12971 | I42: 9905 | J42: 10,171 | K42: 12115 | L42: 14,921 | M42: 20360 | N42: 29817
A43: Total shareholders' equity | B43: 16893 | C43: 18774 | D43: 21147 | E43: 23798 | F43: 26612 | G43: 26320 | H43: 23851 | I43: 21349 | J43: 22,101 | K43: 24520 | L43: 27,501 | M43: 33265 | N43: 42978
A44: Total liabilities and shareholders' equity | B44: 28791 | C44: 30796 | D44: 38650 | E44: 40632 | F44: 44187 | G44: 45212 | H44: 43476 | I44: 40488 | J44: 41,182 | K44: 44460 | L44: 49,555 | M44: 54148 | N44: 65728

Sheet Cash Flow Statement
A2: Cash Flow Statement
A3: All figures in millions USD (except per-share amounts)
A6: Fiscal Year | B6: Q1 2021 | C6: Q2 2021 | D6: Q3 2021 | E6: Q4 2021 | F6: Q1 2022 | G6: Q2 2022 | H6: Q3 2022 | I6: Q4 2022 | J6: Q1 2023 | K6: Q2 2023 | L6: Q3 2023 | M6: Q4 2023 | N6: Q1 2024 | O6: Q2 2024 | P6: Q3 2024 | Q6: Q4 2024 | R6: Q1 2025 | S6: Q2 2025
A7: Quarterly Date | B7: 44318 | C7: 44409 | D7: 44500 | E7: 44591 | F7: 44682 | G7: 44773 | H7: 44864 | I7: 44955 | J7: 45046 | K7: 45137 | L7: 45228 | M7: 45319 | N7: 45410 | O7: 45501 | P7: 45592 | Q7: 45683 | R7: 45774 | S7: 45865
A9: Cash flows from operating activities:
A10: Net income | B10: 1912 | C10: 4285 | D10: 6749 | E10: 9752 | F10: 1618 | G10: 2274 | H10: 2954 | I10: 4368 | J10: 2043 | K10: 8232 | L10: 17475 | M10: 29760 | N10: 14881 | O10: 31480 | P10: 50789 | Q10: 72880 | R10: 18775 | S10: 45197
A11: Adjustments to reconcile net income to net cash provided by operating activities:
A12: Acquisition termination cost | B12: — | C12: — | D12: — | E12: — | F12: 1353 | G12: 1353 | H12: 1353 | I12: 1353 | J12: — | K12: — | L12: — | M12: — | N12: — | O12: — | P12: — | Q12: — | R12: — | S12: —
A13: Stock-based compensation expense | B13: 429 | C13: 894 | D13: 1453 | E13: 2004 | F13: 578 | G13: 1226 | H13: 1971 | I13: 2709 | J13: 735 | K13: 1576 | L13: 2555 | M13: 3549 | N13: 1011 | O13: 2164 | P13: 3416 | Q13: 4737 | R13: 1474 | S13: 3099
A14: Depreciation and amortization | B14: 281 | C14: 567 | D14: 865 | E14: 1174 | F14: 334 | G14: 712 | H14: 1118 | I14: 1544 | J14: 384 | K14: 749 | L14: 1121 | M14: 1508 | N14: 410 | O14: 843 | P14: 1321 | Q14: 1864 | R14: 611 | S14: 1280
A15: Deferred income taxes | B15: 24 | C15: -161 | D15: -182 | E15: -406 | F15: -542 | G15: -985 | H15: -1517 | I15: -2164 | J15: -1135 | K15: -1881 | L15: -2411 | M15: -2489 | N15: -1577 | O15: -3276 | P15: -3879 | Q15: -4477 | R15: -2177 | S15: -2160
A16: (Gains) losses on investments in non-affiliates, net | B16: -133 | C16: -133 | D16: -152 | E16: -100 | F16: 17 | G16: 24 | H16: 35 | I16: 45 | J16: 14 | K16: -45 | L16: 24 | M16: -238 | N16: -69 | O16: -264 | P16: -302 | Q16: -1030 | R16: 175 | S16: -2073
A17: Other | B17: -3 | C17: 16 | D17: 25 | E17: 47 | F17: 23 | G17: 18 | H17: -27 | I17: -7 | J17: -34 | K17: -102 | L17: -170 | M17: -278 | N17: -145 | O17: -288 | P17: -365 | Q17: -502 | R17: -98 | S17: -196
A18: Changes in operating assets and liabilities, net of acquisitions:
A19: Accounts receivable | B19: -595 | C19: -1157 | D19: -1523 | E19: -2215 | F19: -788 | G19: -668 | H19: -258 | I19: 822 | J19: -252 | K19: -3239 | L19: -4482 | M19: -6172 | N19: -2366 | O19: -4133 | P19: -7694 | Q19: -13063 | R19: 933 | S19: -4743
A20: Inventories | B20: -159 | C20: -282 | D20: -400 | E20: -774 | F20: -560 | G20: -1285 | H20: -1848 | I20: -2554 | J20: 566 | K20: 861 | L20: 405 | M20: -98 | N20: -577 | O20: -1380 | P20: -2357 | Q20: -4781 | R20: -1258 | S20: -4880
A21: Prepaid expenses and other assets | B21: 2 | C21: 18 | D21: -1557 | E21: -1715 | F21: -1261 | G21: -1554 | H21: -1307 | I21: -1517 | J21: -215 | K21: -592 | L21: -337 | M21: -1522 | N21: -726 | O21: -12 | P21: -726 | Q21: -395 | R21: 560 | S21: 946
A22: Accounts payable | B22: 36 | C22: 245 | D22: 474 | E22: 568 | F22: 255 | G22: 559 | H22: -358 | I22: -551 | J22: 11 | K22: 789 | L22: 1250 | M22: 1531 | N22: -22 | O22: 801 | P22: 2490 | Q22: 3357 | R22: 941 | S22: 2255
A23: Accrued and other current liabilities | B23: 33 | C23: 166 | D23: 70 | E23: 581 | F23: 634 | G23: 1267 | H23: 1175 | I23: 1341 | J23: 689 | K23: 2675 | L23: 953 | M23: 2025 | N23: 4202 | O23: 3314 | P23: 3918 | Q23: 4278 | R23: 7128 | S23: 3075
A24: Other long-term liabilities | B24: 47 | C24: 98 | D24: 253 | E24: 192 | F24: 70 | G24: 60 | H24: 102 | I24: 252 | J24: 105 | K24: 236 | L24: 208 | M24: 514 | N24: 323 | O24: 584 | P24: 349 | Q24: 1221 | R24: 350 | S24: 979
A25: Net cash provided by operating activities | B25: 1874 | C25: 4556 | D25: 6075 | E25: 9108 | F25: 1731 | G25: 3001 | H25: 3393 | I25: 5641 | J25: 2911 | K25: 9259 | L25: 16591 | M25: 28090 | N25: 15345 | O25: 29833 | P25: 47460 | Q25: 64089 | R25: 27414 | S25: 42779
A27: Cash flows from investing activities:
A28: Proceeds from maturities of marketable securities | B28: 3140 | C28: 5236 | D28: 7780 | E28: 15197 | F28: 5947 | G28: 10983 | H28: 16792 | I28: 19425 | J28: 2512 | K28: 5111 | L28: 8001 | M28: 9732 | N28: 4004 | O28: 8098 | P28: 9485 | Q28: 11195 | R28: 3122 | S28: 6252
A29: Proceeds from sales of marketable securities | B29: 358 | C29: 705 | D29: 916 | E29: 1023 | F29: 1029 | G29: 1731 | H29: 1806 | I29: 1806 | J29: — | K29: — | L29: — | M29: 50 | N29: 149 | O29: 164 | P29: 318 | Q29: 495 | R29: 467 | S29: 487
A30: Purchases of marketable securities | B30: -4470 | C30: -9268 | D30: -16020 | E30: -24787 | F30: -3932 | G30: -7576 | H30: -9764 | I30: -11897 | J30: -2801 | K30: -5343 | L30: -10688 | M30: -18211 | N30: -9303 | O30: -15047 | P30: -19565 | Q30: -26575 | R30: -6546 | S30: -14358
A31: Purchases related to property and equipment and intangible assets | B31: -298 | C31: -481 | D31: -703 | E31: -976 | F31: -361 | G31: -794 | H31: -1324 | I31: -1833 | J31: -248 | K31: -537 | L31: -815 | M31: -1069 | N31: -369 | O31: -1346 | P31: -2159 | Q31: -3236 | R31: -1227 | S31: -3122
A32: Investments and other, net | B32: -2 | C32: 3 | D32: -203 | E32: -24 | F32: -36 | G32: -49 | H32: -49 | I32: -49 | J32: -221 | K32: -435 | L32: -872 | M32: -985 | N32: -135 | O32: -429 | P32: -837 | Q32: -456 | R32: -649 | S32: -995
A33: Acquisitions, net of cash acquired | B33: — | C33: — | D33: -14 | E33: -263 | F33: -35 | G33: -65 | H33: -83 | I33: -77 | J33: -83 | K33: -83 | L33: -83 | M33: -83 | N33: -39 | O33: -317 | P33: -465 | Q33: -1007 | R33: -383 | S33: -677
A34: Net cash used in investing activities | B34: -1272 | C34: -3805 | D34: -8244 | E34: -9830 | F34: 2612 | G34: 4230 | H34: 7378 | I34: 7375 | J34: -841 | K34: -1287 | L34: -4457 | M34: -10566 | N34: -5693 | O34: -8877 | P34: -13223 | Q34: -20421 | R34: -5216 | S34: -12343
A36: Cash flows from financing activities:
A37: Issuance of debt, net of issuance costs | B37: — | C37: 4985 | D37: 4977 | E37: 4977 | F37: — | G37: — | H37: — | I37: — | J37: — | K37: — | L37: — | M37: — | N37: — | O37: — | P37: — | Q37: — | R37: — | S37: —
A38: Proceeds related to employee stock plans | B38: 126 | C38: 128 | D38: 277 | E38: 281 | F38: 204 | G38: 205 | H38: 349 | I38: 355 | J38: 246 | K38: 247 | L38: 403 | M38: 403 | N38: 285 | O38: 285 | P38: 489 | Q38: 490 | R38: 370 | S38: 370
A39: Payments related to repurchases of common stock | B39: — | C39: — | D39: — | E39: — | F39: -1996 | G39: -5341 | H39: -8826 | I39: -10039 | J39: — | K39: -3067 | L39: -6874 | M39: -9533 | N39: -7740 | O39: -14898 | P39: -25895 | Q39: -33706 | R39: -14095 | S39: -23815
A40: Payments related to tax on restricted stock units | B40: -477 | C40: -843 | D40: -1282 | E40: -1904 | F40: -532 | G40: -837 | H40: -1131 | I40: -1475 | J40: -507 | K40: -1179 | L40: -1942 | M40: -2783 | N40: -1752 | O40: -3389 | P40: -5068 | Q40: -6930 | R40: -1532 | S40: -3380
A41: Dividends paid | B41: -99 | C41: -198 | D41: -298 | E41: -399 | F41: -100 | G41: -200 | H41: -300 | I41: -398 | J41: -99 | K41: -199 | L41: -296 | M41: -395 | N41: -98 | O41: -344 | P41: -589 | Q41: -834 | R41: -244 | S41: -488
A42: Principal payments on property and equipment | B42: -19 | C42: -40 | D42: -62 | F42: -22 | G42: -36 | H42: -54 | I42: -58 | J42: -20 | K42: -31 | L42: -44 | M42: -74 | N42: -40 | O42: -69 | P42: -97 | Q42: -129 | R42: -52 | S42: -73
A43: Repayment of debt | B43: — | C43: — | D43: -1000 | E43: -1000 | F43: — | G43: — | H43: — | I43: — | J43: — | K43: -1250 | L43: -1250 | M43: -1250 | N43: — | O43: -1250 | P43: — | Q43: -1250 | R43: — | S43: —
A44: Other | B44: -2 | C44: -2 | D44: -2 | E44: -7 | F44: — | G44: 1 | H44: 1 | I44: -2 | J44: — | K44: — | L44: -1 | M44: -1 | N44: — | O44: — | P44: — | Q44: — | R44: — | S44: —
A45: Net cash provided by (used in) financing activities | B45: -471 | C45: 4030 | D45: 2610 | E45: 1865 | F45: -2446 | G45: -6208 | H45: -9961 | I45: -11617 | J45: -380 | K45: -5479 | L45: -10004 | M45: -13633 | N45: -9345 | O45: -19665 | P45: -32410 | Q45: -42359 | R45: -15553 | S45: -27386
A47: Change in cash and cash equivalents | B47: 131 | C47: 4781 | D47: 441 | E47: 1143 | F47: 1897 | G47: 1023 | H47: 810 | I47: 1399 | J47: 1690 | K47: 2493 | L47: 2130 | M47: 3891 | N47: 307 | O47: 1291 | P47: 1827 | Q47: 1309 | R47: 6645 | S47: 3050
A48: Cash and cash equivalents at beginning of period | B48: 847 | C48: 847 | D48: 847 | E48: 847 | F48: 1990 | G48: 1990 | H48: 1990 | I48: 1990 | J48: 3389 | K48: 3389 | L48: 3389 | M48: 3389 | N48: 7280 | O48: 7280 | P48: 7280 | Q48: 7280 | R48: 8589 | S48: 8589
A49: Cash and cash equivalents at end of period | B49: 978 | C49: 5628 | D49: 1288 | E49: 1990 | F49: 3887 | G49: 3013 | H49: 2800 | I49: 3389 | J49: 5079 | K49: 5882 | L49: 5519 | M49: 7280 | N49: 7587 | O49: 8571 | P49: 9107 | Q49: 8589 | R49: 15234 | S49: 11639
A51: Supplemental disclosures of cash flow information:
A52: Cash paid for income taxes, net | B52: — | C52: 241 | D52: 313 | E52: 396 | F52: — | G52: 1108 | H52: 1372 | I52: 1404 | J52: — | K52: 328 | L52: 4676 | M52: 6549 | N52: — | O52: 7449 | P52: 10989 | Q52: 15118 | R52: — | S52: 8451
A53: Cash paid for interest | B53: — | C53: — | D53: — | E53: 246 | F53: — | G53: — | H53: — | I53: 254 | J53: — | K53: — | L53: — | M53: 252 | N53: — | O53: — | P53: — | Q53: 246 | R53: — | S53: —
A54: Accumulated Amortization of Intangible Assets | B54: 137 | C54: 138 | D54: 143 | E54: 145 | F54: 155 | G54: 182 | H54: 181 | I54: 181 | J54: 181 | K54: 146 | L54: 144 | M54: 143 | N54: 181 | O54: 181 | P54: 181 | Q54: 146 | R54: 144 | S54: 143
A55: Total Annual | B55: =B54 -> 137 | C55: =C54+B55 -> 275 | D55: =D54+C55 -> 418 | E55: =E54+D55 -> 563 | F55: =F54 -> 155 | G55: =G54+F55 -> 337 | H55: =H54+G55 -> 518 | I55: =I54+H55 -> 699 | J55: =J54 -> 181 | K55: =K54+J55 -> 327 | L55: =L54+K55 -> 471 | M55: =M54+L55 -> 614 | N55: 795 | O55: 976 | P55: 1157 | Q55: 1303 | R55: 1447 | S55: 1590

Sheet Working Capital
A2: Working Capital Schedule
D4: Historical | W4: Projected
A5: $ in millions | D5: Q4 2021 | E5: Q1 2022 | F5: =IF(MID(E5,2,1)="4","Q1 "&RIGHT(E5,4)+1, "Q"&MID(E5,2,1)+1&" "&RIGHT(E5,4)) -> Q2 2022 | G5: =IF(MID(F5,2,1)="4","Q1 "&RIGHT(F5,4)+1, "Q"&MID(F5,2,1)+1&" "&RIGHT(F5,4)) -> Q3 2022 | H5: =IF(MID(G5,2,1)="4","Q1 "&RIGHT(G5,4)+1, "Q"&MID(G5,2,1)+1&" "&RIGHT(G5,4)) -> Q4 2022 | I5: =IF(MID(H5,2,1)="4","Q1 "&RIGHT(H5,4)+1, "Q"&MID(H5,2,1)+1&" "&RIGHT(H5,4)) -> Q1 2023 | J5: =IF(MID(I5,2,1)="4","Q1 "&RIGHT(I5,4)+1, "Q"&MID(I5,2,1)+1&" "&RIGHT(I5,4)) -> Q2 2023 | K5: =IF(MID(J5,2,1)="4","Q1 "&RIGHT(J5,4)+1, "Q"&MID(J5,2,1)+1&" "&RIGHT(J5,4)) -> Q3 2023 | L5: =IF(MID(K5,2,1)="4","Q1 "&RIGHT(K5,4)+1, "Q"&MID(K5,2,1)+1&" "&RIGHT(K5,4)) -> Q4 2023 | M5: =IF(MID(L5,2,1)="4","Q1 "&RIGHT(L5,4)+1, "Q"&MID(L5,2,1)+1&" "&RIGHT(L5,4)) -> Q1 2024 | ... AF5: =IF(MID(AE5,2,1)="4","Q1 "&RIGHT(AE5,4)+1, "Q"&MID(AE5,2,1)+1&" "&RIGHT(AE5,4)) -> Q4 2028
A6: Current assets
A7: Accounts Receivables | D7: ='Balance Sheet'!B13 -> 2429 | E7: ='Balance Sheet'!C13 -> 3024 | F7: ='Balance Sheet'!D13 -> 3586 | G7: ='Balance Sheet'!E13 -> 3954 | H7: ='Balance Sheet'!F13 -> 4650 | I7: ='Balance Sheet'!G13 -> 5438 | J7: ='Balance Sheet'!H13 -> 5317 | K7: ='Balance Sheet'!I13 -> 4908 | ... V7: ='Balance Sheet'!T13 -> 27808 | W7: =(W20/90)*'DCF Valuation'!X$10 -> 22596.662 | X7: =(X20/90)*'DCF Valuation'!Y$10 -> 22898.681 | Y7: =(Y20/90)*'DCF Valuation'!Z$10 -> 26792.062 | Z7: =(Z20/90)*'DCF Valuation'!AA$10 -> 31346.646 | AA7: =(AA20/90)*'DCF Valuation'!AB$10 -> 37152.18 | AB7: =(AB20/90)*'DCF Valuation'!AC$10 -> 43751.348 | AC7: =(AC20/90)*'DCF Valuation'!AD$10 -> 53778.959 | AD7: =(AD20/90)*'DCF Valuation'!AE$10 -> 66342.77 | ... AF7: =(AF20/90)*'DCF Valuation'!AG$10 -> 100665.31
A8: Inventories | D8: ='Balance Sheet'!B14 -> 1826 | E8: ='Balance Sheet'!C14 -> 1992 | F8: ='Balance Sheet'!D14 -> 2114 | G8: ='Balance Sheet'!E14 -> 2233 | H8: ='Balance Sheet'!F14 -> 2605 | I8: ='Balance Sheet'!G14 -> 3163 | J8: ='Balance Sheet'!H14 -> 3889 | K8: ='Balance Sheet'!I14 -> 4454 | ... V8: ='Balance Sheet'!T14 -> 14962 | W8: =(W21/90)*('DCF Valuation'!X$10-'DCF Valuation'!X$13) -> 10504.652 | X8: =(X21/90)*('DCF Valuation'!Y$10-'DCF Valuation'!Y$13) -> 13414.885 | Y8: =(Y21/90)*('DCF Valuation'!Z$10-'DCF Valuation'!Z$13) -> 15466.739 | Z8: =(Z21/90)*('DCF Valuation'!AA$10-'DCF Valuation'!AA$13) -> 18541.15 | AA8: =(AA21/90)*('DCF Valuation'!AB$10-'DCF Valuation'!AB$13) -> 20144.947 | AB8: =(AB21/90)*('DCF Valuation'!AC$10-'DCF Valuation'!AC$13) -> 24276.404 | AC8: =(AC21/90)*('DCF Valuation'!AD$10-'DCF Valuation'!AD$13) -> 30880.417 | AD8: =(AD21/90)*('DCF Valuation'!AE$10-'DCF Valuation'!AE$13) -> 37581.116 | ... AF8: =(AF21/90)*('DCF Valuation'!AG$10-'DCF Valuation'!AG$13) -> 56316.674
A9: Prepaid expenses and other current assets | D9: ='Balance Sheet'!B15 -> 239 | E9: ='Balance Sheet'!C15 -> 444 | F9: ='Balance Sheet'!D15 -> 452 | G9: ='Balance Sheet'!E15 -> 321 | H9: ='Balance Sheet'!F15 -> 366 | I9: ='Balance Sheet'!G15 -> 636 | J9: ='Balance Sheet'!H15 -> 1175 | K9: ='Balance Sheet'!I15 -> 718 | ... V9: ='Balance Sheet'!T15 -> 2658 | W9: =W22*'DCF Valuation'!X$10 -> 4053.7616 | X9: =X22*'DCF Valuation'!Y$10 -> 4107.9428 | Y9: =Y22*'DCF Valuation'!Z$10 -> 4806.4017 | Z9: =Z22*'DCF Valuation'!AA$10 -> 5623.478 | AA9: =AA22*'DCF Valuation'!AB$10 -> 6664.9704 | AB9: =AB22*'DCF Valuation'!AC$10 -> 7848.838 | AC9: =AC22*'DCF Valuation'!AD$10 -> 9647.7562 | AD9: =AD22*'DCF Valuation'!AE$10 -> 11901.66 | ... AF9: =AF22*'DCF Valuation'!AG$10 -> 18059.002
A10: Total current assets | D10: =D7+D8+D9 -> 4494 | E10: =E7+E8+E9 -> 5460 | F10: =F7+F8+F9 -> 6152 | G10: =G7+G8+G9 -> 6508 | H10: =H7+H8+H9 -> 7621 | I10: =I7+I8+I9 -> 9237 | J10: =J7+J8+J9 -> 10381 | K10: =K7+K8+K9 -> 10080 | ... AF10: =AF7+AF8+AF9 -> 175040.98
A12: Current liabilities
A13: Accounts Payables | D13: ='Balance Sheet'!B27 -> 1201 | E13: ='Balance Sheet'!C27 -> 1218 | F13: ='Balance Sheet'!D27 -> 1474 | G13: ='Balance Sheet'!E27 -> 1664 | H13: ='Balance Sheet'!F27 -> 1783 | I13: ='Balance Sheet'!G27 -> 1999 | J13: ='Balance Sheet'!H27 -> 2421 | K13: ='Balance Sheet'!I27 -> 1491 | ... V13: ='Balance Sheet'!T27 -> 9064 | W13: =(W23/90)*('DCF Valuation'!X$10-'DCF Valuation'!X$13) -> 5291.2428 | X13: =(X23/90)*('DCF Valuation'!Y$10-'DCF Valuation'!Y$13) -> 6757.1407 | Y13: =(Y23/90)*('DCF Valuation'!Z$10-'DCF Valuation'!Z$13) -> 7790.6691 | Z13: =(Z23/90)*('DCF Valuation'!AA$10-'DCF Valuation'!AA$13) -> 9339.2647 | AA13: =(AA23/90)*('DCF Valuation'!AB$10-'DCF Valuation'!AB$13) -> 10147.105 | AB13: =(AB23/90)*('DCF Valuation'!AC$10-'DCF Valuation'!AC$13) -> 12228.139 | AC13: =(AC23/90)*('DCF Valuation'!AD$10-'DCF Valuation'!AD$13) -> 15554.612 | AD13: =(AD23/90)*('DCF Valuation'!AE$10-'DCF Valuation'!AE$13) -> 18929.785 | ... AF13: =(AF23/90)*('DCF Valuation'!AG$10-'DCF Valuation'!AG$13) -> 28366.974
A14: Accrued and other current liabilities | D14: ='Balance Sheet'!B28 -> 1725 | E14: ='Balance Sheet'!C28 -> 1787 | F14: ='Balance Sheet'!D28 -> 1974 | G14: ='Balance Sheet'!E28 -> 1948 | H14: ='Balance Sheet'!F28 -> 2552 | I14: ='Balance Sheet'!G28 -> 3563 | J14: ='Balance Sheet'!H28 -> 3903 | K14: ='Balance Sheet'!I28 -> 4115 | ... V14: ='Balance Sheet'!T28 -> 15193 | W14: =W24*('DCF Valuation'!X$13-'DCF Valuation'!X$16) -> 7588.8381 | X14: =X24*('DCF Valuation'!Y$13-'DCF Valuation'!Y$16) -> 7588.8381 | Y14: =Y24*('DCF Valuation'!Z$13-'DCF Valuation'!Z$16) -> 7588.8381 | Z14: =Z24*('DCF Valuation'!AA$13-'DCF Valuation'!AA$16) -> 7588.8381 | AA14: =AA24*('DCF Valuation'!AB$13-'DCF Valuation'!AB$16) -> 7588.8381 | AB14: =AB24*('DCF Valuation'!AC$13-'DCF Valuation'!AC$16) -> 7588.8381 | AC14: =AC24*('DCF Valuation'!AD$13-'DCF Valuation'!AD$16) -> 7588.8381 | AD14: =AD24*('DCF Valuation'!AE$13-'DCF Valuation'!AE$16) -> 7588.8381 | ... AF14: =AF24*('DCF Valuation'!AG$13-'DCF Valuation'!AG$16) -> 7588.8381
A15: Total current liabilities | D15: =D13+D14 -> 2926 | E15: =E13+E14 -> 3005 | F15: =F13+F14 -> 3448 | G15: =G13+G14 -> 3612 | H15: =H13+H14 -> 4335 | I15: =I13+I14 -> 5562 | J15: =J13+J14 -> 6324 | K15: =K13+K14 -> 5606 | ... AF15: =AF13+AF14 -> 35955.812
A17: Net Working capital | D17: =D10-D15 -> 1568 | E17: =E10-E15 -> 2455 | F17: =F10-F15 -> 2704 | G17: =G10-G15 -> 2896 | H17: =H10-H15 -> 3286 | I17: =I10-I15 -> 3675 | J17: =J10-J15 -> 4057 | K17: =K10-K15 -> 4474 | ... AF17: =AF10-AF15 -> 139085.17
A18: Changes in working capital | E18: =E17-D17 -> 887 | F18: =F17-E17 -> 249 | G18: =G17-F17 -> 192 | H18: =H17-G17 -> 390 | I18: =I17-H17 -> 389 | J18: =J17-I17 -> 382 | K18: =K17-J17 -> 417 | L18: =L17-K17 -> -10 | ... AF18: =AF17-AE17 -> 27169.625
A20: Days Sales Outstanding (DSO) | E20: =(AVERAGE(E7,D7)/'DCF Valuation'!F10)*90 -> 43.346582 | F20: =(AVERAGE(F7,E7)/'DCF Valuation'!G10)*90 -> 45.71231 | G20: =(AVERAGE(G7,F7)/'DCF Valuation'!H10)*90 -> 47.768549 | H20: =(AVERAGE(H7,G7)/'DCF Valuation'!I10)*90 -> 50.658119 | I20: =(AVERAGE(I7,H7)/'DCF Valuation'!J10)*90 -> 54.773166 | J20: =(AVERAGE(J7,I7)/'DCF Valuation'!K10)*90 -> 72.191975 | K20: =(AVERAGE(K7,J7)/'DCF Valuation'!L10)*90 -> 77.579666 | L20: =(AVERAGE(L7,K7)/'DCF Valuation'!M10)*90 -> 72.999504 | ... P20: =(AVERAGE(P7,O7)/'DCF Valuation'!Q10)*90 -> 37.273673 | Q20: =(AVERAGE(Q7,P7)/'DCF Valuation'!X10)*90 -> 21.21598 | R20: =(AVERAGE(R7,Q7)/'DCF Valuation'!Y10)*90 -> 24.80528 | S20: =(AVERAGE(S7,R7)/'DCF Valuation'!Z10)*90 -> 25.463621 | T20: =(AVERAGE(T7,S7)/'DCF Valuation'!AA10)*90 -> 27.872741 | U20: =(AVERAGE(U7,T7)/'DCF Valuation'!AB10)*90 -> 26.078536 | V20: =(AVERAGE(V7,U7)/'DCF Valuation'!AC10)*90 -> 24.468931 | W20: =AVERAGE($E20:$V20) -> 42.873396 | X20: =AVERAGE($E20:$V20) -> 42.873396 | Y20: =AVERAGE($E20:$V20) -> 42.873396 | Z20: =AVERAGE($E20:$V20) -> 42.873396 | AA20: =AVERAGE($E20:$V20) -> 42.873396 | AB20: =AVERAGE($E20:$V20) -> 42.873396 | AC20: =AVERAGE($E20:$V20) -> 42.873396 | AD20: =AVERAGE($E20:$V20) -> 42.873396 | ... AF20: =AVERAGE($E20:$V20) -> 42.873396
A21: Days Inventory Outstanding (DIO) | E21: =(AVERAGE(E8,D8)/('DCF Valuation'!F10-'DCF Valuation'!F13))*90 -> 84.552165 | F21: =(AVERAGE(F8,E8)/('DCF Valuation'!G10-'DCF Valuation'!G13))*90 -> 80.615183 | G21: =(AVERAGE(G8,F8)/('DCF Valuation'!H10-'DCF Valuation'!H13))*90 -> 79.132282 | H21: =(AVERAGE(H8,G8)/('DCF Valuation'!I10-'DCF Valuation'!I13))*90 -> 82.372304 | I21: =(AVERAGE(I8,H8)/('DCF Valuation'!J10-'DCF Valuation'!J13))*90 -> 90.850543 | J21: =(AVERAGE(J8,I8)/('DCF Valuation'!K10-'DCF Valuation'!K13))*90 -> 83.752969 | K21: =(AVERAGE(K8,J8)/('DCF Valuation'!L10-'DCF Valuation'!L13))*90 -> 136.32353 | L21: =(AVERAGE(L8,K8)/('DCF Valuation'!M10-'DCF Valuation'!M13))*90 -> 180.73039 | ... P21: =(AVERAGE(P8,O8)/('DCF Valuation'!Q10-'DCF Valuation'!Q13))*90 -> 85.23061 | Q21: =(AVERAGE(Q8,P8)/('DCF Valuation'!X10-'DCF Valuation'!X13))*90 -> 44.61535 | R21: =(AVERAGE(R8,Q8)/('DCF Valuation'!Y10-'DCF Valuation'!Y13))*90 -> 39.302746 | S21: =(AVERAGE(S8,R8)/('DCF Valuation'!Z10-'DCF Valuation'!Z13))*90 -> 38.955078 | T21: =(AVERAGE(T8,S8)/('DCF Valuation'!AA10-'DCF Valuation'!AA13))*90 -> 40.217676 | U21: =(AVERAGE(U8,T8)/('DCF Valuation'!AB10-'DCF Valuation'!AB13))*90 -> 44.694937 | V21: =(AVERAGE(V8,U8)/('DCF Valuation'!AC10-'DCF Valuation'!AC13))*90 -> 45.544482 | W21: =AVERAGE($E21:$V21) -> 84.096309 | X21: =AVERAGE($E21:$V21) -> 84.096309 | Y21: =AVERAGE($E21:$V21) -> 84.096309 | Z21: =AVERAGE($E21:$V21) -> 84.096309 | AA21: =AVERAGE($E21:$V21) -> 84.096309 | AB21: =AVERAGE($E21:$V21) -> 84.096309 | AC21: =AVERAGE($E21:$V21) -> 84.096309 | AD21: =AVERAGE($E21:$V21) -> 84.096309 | ... AF21: =AVERAGE($E21:$V21) -> 84.096309
A22: Other current assets (% of revenue) | E22: =E9/'DCF Valuation'!F10 -> 0.078431373 | F22: =F9/'DCF Valuation'!G10 -> 0.069463655 | G22: =G9/'DCF Valuation'!H10 -> 0.045192172 | H22: =H9/'DCF Valuation'!I10 -> 0.047886955 | I22: =I9/'DCF Valuation'!J10 -> 0.076737452 | J22: =J9/'DCF Valuation'!K10 -> 0.1752685 | K22: =K9/'DCF Valuation'!L10 -> 0.12105884 | L22: =L9/'DCF Valuation'!M10 -> 0.13072219 | ... P22: =P9/'DCF Valuation'!Q10 -> 0.1393476 | Q22: =Q9/'DCF Valuation'!X10 -> 0.085632971 | R22: =R9/'DCF Valuation'!Y10 -> 0.083754603 | S22: =S9/'DCF Valuation'!Z10 -> 0.067671847 | T22: =T9/'DCF Valuation'!AA10 -> 0.057307418 | U22: =U9/'DCF Valuation'!AB10 -> 0.035632773 | V22: =V9/'DCF Valuation'!AC10 -> 0.028940692 | W22: =AVERAGE($E22:$V22) -> 0.085459295 | X22: =AVERAGE($E22:$V22) -> 0.085459295 | Y22: =AVERAGE($E22:$V22) -> 0.085459295 | Z22: =AVERAGE($E22:$V22) -> 0.085459295 | AA22: =AVERAGE($E22:$V22) -> 0.085459295 | AB22: =AVERAGE($E22:$V22) -> 0.085459295 | AC22: =AVERAGE($E22:$V22) -> 0.085459295 | AD22: =AVERAGE($E22:$V22) -> 0.085459295 | ... AF22: =AVERAGE($E22:$V22) -> 0.085459295
A23: Days Payable Outstanding (DPO) | E23: =(AVERAGE(E13,D13)/('DCF Valuation'!F10-'DCF Valuation'!F13))*90 -> 53.570374 | F23: =(AVERAGE(F13,E13)/('DCF Valuation'!G10-'DCF Valuation'!G13))*90 -> 52.853403 | G23: =(AVERAGE(G13,F13)/('DCF Valuation'!H10-'DCF Valuation'!H13))*90 -> 57.123786 | H23: =(AVERAGE(H13,G13)/('DCF Valuation'!I10-'DCF Valuation'!I13))*90 -> 58.68899 | I23: =(AVERAGE(I13,H13)/('DCF Valuation'!J10-'DCF Valuation'!J13))*90 -> 59.569478 | J23: =(AVERAGE(J13,I13)/('DCF Valuation'!K10-'DCF Valuation'!K13))*90 -> 52.494062 | K23: =(AVERAGE(K13,J13)/('DCF Valuation'!L10-'DCF Valuation'!L13))*90 -> 63.921569 | L23: =(AVERAGE(L13,K13)/('DCF Valuation'!M10-'DCF Valuation'!M13))*90 -> 60.500451 | ... P23: =(AVERAGE(P13,O13)/('DCF Valuation'!Q10-'DCF Valuation'!Q13))*90 -> 43.026167 | Q23: =(AVERAGE(Q13,P13)/('DCF Valuation'!X10-'DCF Valuation'!X13))*90 -> 21.671228 | R23: =(AVERAGE(R13,Q13)/('DCF Valuation'!Y10-'DCF Valuation'!Y13))*90 -> 20.044745 | S23: =(AVERAGE(S13,R13)/('DCF Valuation'!Z10-'DCF Valuation'!Z13))*90 -> 24.557277 | T23: =(AVERAGE(T13,S13)/('DCF Valuation'!AA10-'DCF Valuation'!AA13))*90 -> 26.449687 | U23: =(AVERAGE(U13,T13)/('DCF Valuation'!AB10-'DCF Valuation'!AB13))*90 -> 28.472593 | V23: =(AVERAGE(V13,U13)/('DCF Valuation'!AC10-'DCF Valuation'!AC13))*90 -> 28.397101 | W23: =AVERAGE($E23:$V23) -> 42.359707 | X23: =AVERAGE($E23:$V23) -> 42.359707 | Y23: =AVERAGE($E23:$V23) -> 42.359707 | Z23: =AVERAGE($E23:$V23) -> 42.359707 | AA23: =AVERAGE($E23:$V23) -> 42.359707 | AB23: =AVERAGE($E23:$V23) -> 42.359707 | AC23: =AVERAGE($E23:$V23) -> 42.359707 | AD23: =AVERAGE($E23:$V23) -> 42.359707 | ... AF23: =AVERAGE($E23:$V23) -> 42.359707
A24: Accrued and other current liabilities | E24: =E14/'Income Statement'!B17 -> 1.0830303 | F24: =F14/'Income Statement'!C17 -> 1.1799163 | G24: =G14/'Income Statement'!D17 -> 1.0999435 | H24: =H14/'Income Statement'!E17 -> 1.3020408 | I24: =I14/'Income Statement'!F17 -> 1.7551724 | J24: =J14/'Income Statement'!G17 -> 1.0954252 | K24: =K14/'Income Statement'!H17 -> 1.7032285 | L24: =L14/'Income Statement'!I17 -> 1.5993789 | ... V24: =V14/'Income Statement'!S17 -> 3.0204771 | W24: =AVERAGE($E24:$V24) -> 2.1682395 | X24: =AVERAGE($E24:$V24) -> 2.1682395 | Y24: =AVERAGE($E24:$V24) -> 2.1682395 | Z24: =AVERAGE($E24:$V24) -> 2.1682395 | AA24: =AVERAGE($E24:$V24) -> 2.1682395 | AB24: =AVERAGE($E24:$V24) -> 2.1682395 | AC24: =AVERAGE($E24:$V24) -> 2.1682395 | AD24: =AVERAGE($E24:$V24) -> 2.1682395 | ... AF24: =AVERAGE($E24:$V24) -> 2.1682395
A25: (% of operating expenses)
A26: Cash Conversion Cycle (CCC) | E26: =E21+E20-E23 -> 74.328373 | F26: =F21+F20-F23 -> 73.47409 | G26: =G21+G20-G23 -> 69.777044 | H26: =H21+H20-H23 -> 74.341433 | I26: =I21+I20-I23 -> 86.05423 | J26: =J21+J20-J23 -> 103.45088 | K26: =K21+K20-K23 -> 149.98163 | L26: =L21+L20-L23 -> 193.22944 | ... V26: =V21+V20-V23 -> 41.616311 | W26: =AVERAGE($E26:$V26) -> 84.609998 | X26: =AVERAGE($E26:$V26) -> 84.609998 | Y26: =AVERAGE($E26:$V26) -> 84.609998 | Z26: =AVERAGE($E26:$V26) -> 84.609998 | AA26: =AVERAGE($E26:$V26) -> 84.609998 | AB26: =AVERAGE($E26:$V26) -> 84.609998 | AC26: =AVERAGE($E26:$V26) -> 84.609998 | AD26: =AVERAGE($E26:$V26) -> 84.609998 | ... AF26: =AVERAGE($E26:$V26) -> 84.609998

Sheet Debt
A2: Debt Schedule
D4: Historical | V4: Projected
A5: $ in millions | D5: Q1 2022 | E5: =IF(MID(D5,2,1)="4","Q1 "&RIGHT(D5,4)+1, "Q"&MID(D5,2,1)+1&" "&RIGHT(D5,4)) -> Q2 2022 | F5: =IF(MID(E5,2,1)="4","Q1 "&RIGHT(E5,4)+1, "Q"&MID(E5,2,1)+1&" "&RIGHT(E5,4)) -> Q3 2022 | G5: =IF(MID(F5,2,1)="4","Q1 "&RIGHT(F5,4)+1, "Q"&MID(F5,2,1)+1&" "&RIGHT(F5,4)) -> Q4 2022 | H5: =IF(MID(G5,2,1)="4","Q1 "&RIGHT(G5,4)+1, "Q"&MID(G5,2,1)+1&" "&RIGHT(G5,4)) -> Q1 2023 | I5: =IF(MID(H5,2,1)="4","Q1 "&RIGHT(H5,4)+1, "Q"&MID(H5,2,1)+1&" "&RIGHT(H5,4)) -> Q2 2023 | J5: =IF(MID(I5,2,1)="4","Q1 "&RIGHT(I5,4)+1, "Q"&MID(I5,2,1)+1&" "&RIGHT(I5,4)) -> Q3 2023 | K5: =IF(MID(J5,2,1)="4","Q1 "&RIGHT(J5,4)+1, "Q"&MID(J5,2,1)+1&" "&RIGHT(J5,4)) -> Q4 2023 | L5: =IF(MID(K5,2,1)="4","Q1 "&RIGHT(K5,4)+1, "Q"&MID(K5,2,1)+1&" "&RIGHT(K5,4)) -> Q1 2024 | ... AE5: =IF(MID(AD5,2,1)="4","Q1 "&RIGHT(AD5,4)+1, "Q"&MID(AD5,2,1)+1&" "&RIGHT(AD5,4)) -> Q4 2028
A6: Opening balance | D6: ='Balance Sheet'!B29+'Balance Sheet'!B31 -> 6963 | E6: ='Balance Sheet'!C29+'Balance Sheet'!C31 -> 6963 | F6: ='Balance Sheet'!D29+'Balance Sheet'!D31 -> 11943 | G6: ='Balance Sheet'!E29+'Balance Sheet'!E31 -> 10944 | H6: ='Balance Sheet'!F29+'Balance Sheet'!F31 -> 10946 | I6: ='Balance Sheet'!G29+'Balance Sheet'!G31 -> 10947 | J6: ='Balance Sheet'!H29+'Balance Sheet'!H31 -> 10949 | K6: ='Balance Sheet'!I29+'Balance Sheet'!I31 -> 10950 | ... U6: ='Balance Sheet'!S29+'Balance Sheet'!S31 -> 8464 | V6: =U8 -> 8466 | W6: =V8 -> 8467 | X6: =W8 -> 7218 | Y6: =X8 -> 7219 | Z6: =Y8 -> 7220 | AA6: =Z8 -> 7221 | AB6: =AA8 -> 7222 | AC6: =AB8 -> 7223 | ... AE6: =AD8 -> 7225
A7: Add/Less: Debt incurred (repaid) | D7: =D8-D6 -> 0 | E7: =E8-E6 -> 4980 | F7: =F8-F6 -> -999 | G7: =G8-G6 -> 2 | H7: =H8-H6 -> 1 | I7: =I8-I6 -> 2 | J7: =J8-J6 -> 1 | K7: =K8-K6 -> 3 | ... U7: =U8-U6 -> 2 | V7: 1 | W7: -1249 | X7: 1 | Y7: 1 | Z7: 1 | AA7: 1 | AB7: 1 | AC7: 1 | AD7: 1 | AE7: 1
A8: Closing Balance | C8: ='Balance Sheet'!B29+'Balance Sheet'!B31 -> 6963 | D8: ='Balance Sheet'!C29+'Balance Sheet'!C31 -> 6963 | E8: ='Balance Sheet'!D29+'Balance Sheet'!D31 -> 11943 | F8: ='Balance Sheet'!E29+'Balance Sheet'!E31 -> 10944 | G8: ='Balance Sheet'!F29+'Balance Sheet'!F31 -> 10946 | H8: ='Balance Sheet'!G29+'Balance Sheet'!G31 -> 10947 | I8: ='Balance Sheet'!H29+'Balance Sheet'!H31 -> 10949 | J8: ='Balance Sheet'!I29+'Balance Sheet'!I31 -> 10950 | ... U8: ='Balance Sheet'!T29+'Balance Sheet'!T31 -> 8466 | V8: =V6+V7 -> 8467 | W8: =W6+W7 -> 7218 | X8: =X6+X7 -> 7219 | Y8: =Y6+Y7 -> 7220 | Z8: =Z6+Z7 -> 7221 | AA8: =AA6+AA7 -> 7222 | AB8: =AB6+AB7 -> 7223 | AC8: =AC6+AC7 -> 7224 | ... AE8: =AE6+AE7 -> 7226
A10: Interest Expenses | D10: ='Income Statement'!C21 -> -53 | E10: ='Income Statement'!D21 -> (60) | F10: ='Income Statement'!E21 -> (62) | G10: ='Income Statement'!F21 -> -61 | H10: ='Income Statement'!G21 -> -68 | I10: ='Income Statement'!H21 -> (65) | J10: ='Income Statement'!I21 -> (65) | K10: ='Income Statement'!J21 -> -64 | ... U10: ='Income Statement'!T21 -> -62 | V10: =V6*V12 -> -55.465806 | W10: =W6*W12 -> -55.472358 | X10: =X6*X12 -> -47.289415 | Y10: =Y6*Y12 -> -47.295967 | Z10: =Z6*Z12 -> -47.302519 | AA10: =AA6*AA12 -> -47.30907 | AB10: =AB6*AB12 -> -47.315622 | AC10: =AC6*AC12 -> -47.322173 | ... AE10: =AE6*AE12 -> -47.335277
A11: Net Interest Expenses | D11: ='Income Statement'!B21+'Income Statement'!$B20 -> -45 | E11: ='Income Statement'!C21+'Income Statement'!$B20 -> -46 | F11: ='Income Statement'!D21+'Income Statement'!$B20 -> -53 | G11: ='Income Statement'!E21+'Income Statement'!$B20 -> -55 | H11: ='Income Statement'!F21+'Income Statement'!$B20 -> -54 | I11: ='Income Statement'!G21+'Income Statement'!$B20 -> -61 | J11: ='Income Statement'!H21+'Income Statement'!$B20 -> -58 | K11: ='Income Statement'!I21+'Income Statement'!$B20 -> -58 | ... U11: ='Income Statement'!S21+'Income Statement'!$B20 -> -56
A12: Interest rate (pre tax) | D12: =D10/D6 -> -0.0076116616 | E12: =E10/E6 -> -0.0086169754 | F12: =F10/F6 -> -0.0051913255 | G12: =G10/G6 -> -0.0055738304 | H12: =H10/H6 -> -0.006212315 | I12: =I10/I6 -> -0.0059376998 | J12: =J10/J6 -> -0.0059366152 | K12: =K10/K6 -> -0.0058447489 | ... U12: =U10/U6 -> -0.0073251418 | V12: =AVERAGE($D12:$U12) -> -0.0065515954 | W12: =AVERAGE($D12:$U12) -> -0.0065515954 | X12: =AVERAGE($D12:$U12) -> -0.0065515954 | Y12: =AVERAGE($D12:$U12) -> -0.0065515954 | Z12: =AVERAGE($D12:$U12) -> -0.0065515954 | AA12: =AVERAGE($D12:$U12) -> -0.0065515954 | AB12: =AVERAGE($D12:$U12) -> -0.0065515954 | AC12: =AVERAGE($D12:$U12) -> -0.0065515954 | ... AE12: =AVERAGE($D12:$U12) -> -0.0065515954

Sheet Fixed Assets
A2: Long-Term Asset Schedule
D4: Historical | V4: Projected
A5: $ in millions | D5: Q1 2022 | E5: =IF(MID(D5,2,1)="4","Q1 "&RIGHT(D5,4)+1, "Q"&MID(D5,2,1)+1&" "&RIGHT(D5,4)) -> Q2 2022 | F5: =IF(MID(E5,2,1)="4","Q1 "&RIGHT(E5,4)+1, "Q"&MID(E5,2,1)+1&" "&RIGHT(E5,4)) -> Q3 2022 | G5: =IF(MID(F5,2,1)="4","Q1 "&RIGHT(F5,4)+1, "Q"&MID(F5,2,1)+1&" "&RIGHT(F5,4)) -> Q4 2022 | H5: =IF(MID(G5,2,1)="4","Q1 "&RIGHT(G5,4)+1, "Q"&MID(G5,2,1)+1&" "&RIGHT(G5,4)) -> Q1 2023 | I5: =IF(MID(H5,2,1)="4","Q1 "&RIGHT(H5,4)+1, "Q"&MID(H5,2,1)+1&" "&RIGHT(H5,4)) -> Q2 2023 | J5: =IF(MID(I5,2,1)="4","Q1 "&RIGHT(I5,4)+1, "Q"&MID(I5,2,1)+1&" "&RIGHT(I5,4)) -> Q3 2023 | K5: =IF(MID(J5,2,1)="4","Q1 "&RIGHT(J5,4)+1, "Q"&MID(J5,2,1)+1&" "&RIGHT(J5,4)) -> Q4 2023 | L5: =IF(MID(K5,2,1)="4","Q1 "&RIGHT(K5,4)+1, "Q"&MID(K5,2,1)+1&" "&RIGHT(K5,4)) -> Q1 2024 | ... AE5: =IF(MID(AD5,2,1)="4","Q1 "&RIGHT(AD5,4)+1, "Q"&MID(AD5,2,1)+1&" "&RIGHT(AD5,4)) -> Q4 2028
A7: Property and Equipment Schedule
A8: Opening balance | D8: ='Balance Sheet'!B17 -> 2149 | E8: ='Balance Sheet'!C17 -> 2268 | F8: ='Balance Sheet'!D17 -> 2364 | G8: ='Balance Sheet'!E17 -> 2509 | H8: ='Balance Sheet'!F17 -> 2778 | I8: ='Balance Sheet'!G17 -> 2916 | J8: ='Balance Sheet'!H17 -> 3233 | K8: ='Balance Sheet'!I17 -> 3774 | ... U8: ='Balance Sheet'!S17 -> 7136 | V8: =U12 -> 9141 | W8: =V12 -> 7419.0108 | X8: =W12 -> 7518.1708 | Y8: =X12 -> 8796.4584 | Z8: =Y12 -> 10291.834 | AA8: =Z12 -> 12197.927 | AB8: =AA12 -> 14364.587 | AC8: =AB12 -> 17656.886 | ... AE8: =AD12 -> 26871.255
A9: Add: Net Purchases | D9: =D10-D8 -> 263 | E9: =E10-E8 -> 244 | F9: =F10-F8 -> 300 | G9: =G10-G8 -> 433 | H9: =H10-H8 -> 317 | I9: =I10-I8 -> 513 | J9: =J10-J8 -> 766 | K9: =K10-K8 -> 278 | ... AE9: =AE10-AE8 -> 4811.0557
A10: Total Fixed Assets | D10: =D12+D11 -> 2412 | E10: =E12+E11 -> 2512 | F10: =F12+F11 -> 2664 | G10: =G12+G11 -> 2942 | H10: =H12+H11 -> 3095 | I10: =I12+I11 -> 3429 | J10: =J12+J11 -> 3999 | K10: =K12+K11 -> 4052 | ... U10: =U12+U11 -> 9667 | V10: ='DCF Valuation'!X10/V16 -> 7111.8292 | W10: ='DCF Valuation'!Y10/W16 -> 7206.8835 | X10: ='DCF Valuation'!Z10/X16 -> 8432.2441 | Y10: ='DCF Valuation'!AA10/Y16 -> 9865.7046 | Z10: ='DCF Valuation'!AB10/Z16 -> 11692.876 | AA10: ='DCF Valuation'!AC10/AA16 -> 13769.827 | AB10: ='DCF Valuation'!AD10/AB16 -> 16925.809 | AC10: ='DCF Valuation'!AE10/AC16 -> 20880.007 | ... AE10: ='DCF Valuation'!AG10/AE16 -> 31682.311
A11: Less: Depreciation | D11: ='DCF Valuation'!F24 -> 144 | E11: ='DCF Valuation'!G24 -> 148 | F11: ='DCF Valuation'!H24 -> 155 | G11: ='DCF Valuation'!I24 -> 164 | H11: ='DCF Valuation'!J24 -> 179 | I11: ='DCF Valuation'!K24 -> 196 | J11: ='DCF Valuation'!L24 -> 225 | K11: ='DCF Valuation'!M24 -> 245 | ... U11: ='DCF Valuation'!W24 -> 526 | V11: =V10*V14 -> -307.18158 | W11: =W10*W14 -> -311.28727 | X11: =X10*X14 -> -364.21432 | Y11: =Y10*Y14 -> -426.12985 | Z11: =Z10*Z14 -> -505.05094 | AA11: =AA10*AA14 -> -594.76079 | AB11: =AB10*AB14 -> -731.07727 | AC11: =AC10*AC14 -> -901.87114 | ... AE11: =AE10*AE14 -> -1368.4556
A12: Closing Balance | C12: ='Balance Sheet'!B17 -> 2149 | D12: ='Balance Sheet'!C17 -> 2268 | E12: ='Balance Sheet'!D17 -> 2364 | F12: ='Balance Sheet'!E17 -> 2509 | G12: ='Balance Sheet'!F17 -> 2778 | H12: ='Balance Sheet'!G17 -> 2916 | I12: ='Balance Sheet'!H17 -> 3233 | J12: ='Balance Sheet'!I17 -> 3774 | ... U12: ='Balance Sheet'!T17 -> 9141 | V12: =V10-V11 -> 7419.0108 | W12: =W10-W11 -> 7518.1708 | X12: =X10-X11 -> 8796.4584 | Y12: =Y10-Y11 -> 10291.834 | Z12: =Z10-Z11 -> 12197.927 | AA12: =AA10-AA11 -> 14364.587 | AB12: =AB10-AB11 -> 17656.886 | AC12: =AC10-AC11 -> 21781.878 | ... AE12: =AE10-AE11 -> 33050.766
A14: Rate of depreciation | D14: =D11/D10 -> 0.059701493 | E14: =E11/E10 -> 0.058917197 | F14: =F11/F10 -> 0.058183183 | G14: =G11/G10 -> 0.055744392 | H14: =H11/H10 -> 0.057835218 | I14: =I11/I10 -> 0.057159522 | J14: =J11/J10 -> 0.056264066 | K14: =K11/K10 -> 0.060463968 | ... U14: =U11/U10 -> 0.054411917 | V14: =AVERAGE($S14:$U14) -> -0.043193048 | W14: =AVERAGE($S14:$U14) -> -0.043193048 | X14: =AVERAGE($S14:$U14) -> -0.043193048 | Y14: =AVERAGE($S14:$U14) -> -0.043193048 | Z14: =AVERAGE($S14:$U14) -> -0.043193048 | AA14: =AVERAGE($S14:$U14) -> -0.043193048 | AB14: =AVERAGE($S14:$U14) -> -0.043193048 | AC14: =AVERAGE($S14:$U14) -> -0.043193048 | ... AE14: =AVERAGE($S14:$U14) -> -0.043193048
A16: Fixed asset turnover ratio | D16: ='DCF Valuation'!F10/D10 -> 2.3470149 | E16: ='DCF Valuation'!G10/E10 -> 2.5903662 | F16: ='DCF Valuation'!H10/F10 -> 2.6662913 | G16: ='DCF Valuation'!I10/G10 -> 2.5978926 | H16: ='DCF Valuation'!J10/H10 -> 2.6778675 | I16: ='DCF Valuation'!K10/I10 -> 1.9550889 | J16: ='DCF Valuation'!L10/J10 -> 1.4831208 | K16: ='DCF Valuation'!M10/K10 -> 1.4933366 | ... U16: ='DCF Valuation'!W10/U10 -> 4.835316 | V16: =AVERAGE($P16:$U16) -> 6.6698733 | W16: =AVERAGE($P16:$U16) -> 6.6698733 | X16: =AVERAGE($P16:$U16) -> 6.6698733 | Y16: =AVERAGE($P16:$U16) -> 6.6698733 | Z16: =AVERAGE($P16:$U16) -> 6.6698733 | AA16: =AVERAGE($P16:$U16) -> 6.6698733 | AB16: =AVERAGE($P16:$U16) -> 6.6698733 | AC16: =AVERAGE($P16:$U16) -> 6.6698733 | ... AE16: =AVERAGE($P16:$U16) -> 6.6698733
A18: Other intangible asset schedule
A19: Opening balance | D19: ='Balance Sheet'!B20 -> 2737 | E19: ='Balance Sheet'!C20 -> 2613 | F19: ='Balance Sheet'!D20 -> 2478 | G19: ='Balance Sheet'!E20 -> 2454 | H19: ='Balance Sheet'!F20 -> 2339 | I19: ='Balance Sheet'!G20 -> 2211 | J19: ='Balance Sheet'!H20 -> 2036 | K19: ='Balance Sheet'!I20 -> 1850 | ... U19: ='Balance Sheet'!S20 -> 769 | V19: =U23 -> 755 | W19: =V23 -> 683.82846 | X19: =W23 -> 628.09185 | Y19: =X23 -> 584.88464 | Z19: =Y23 -> 549.81874 | AA19: =Z23 -> 524.96493 | AB19: =AA23 -> 509.11582 | AC19: =AB23 -> 501.00486 | ... AE19: =AD23 -> 488.10193
A20: Add: Net Purchases | D20: =D21-D19 -> 13 | E20: =E21-E19 -> 3 | F20: =F21-F19 -> 119 | G20: =G21-G19 -> 30 | H20: =H21-H19 -> 27 | I20: =I21-I19 -> 7 | J20: =J21-J19 -> -5 | K20: =K21-K19 -> 7 | ... U20: =U21-U19 -> 129 | V20: =AVERAGE(J20:U20) -> 55.916667 | W20: =AVERAGE(K20:V20) -> 60.993056 | X20: =AVERAGE(L20:W20) -> 65.492477 | Y20: =AVERAGE(M20:X20) -> 67.11685 | Z20: =AVERAGE(N20:Y20) -> 72.709921 | AA20: =AVERAGE(O20:Z20) -> 78.769081 | AB20: =AVERAGE(P20:AA20) -> 84.999838 | AC20: =AVERAGE(Q20:AB20) -> 87.499824 | ... AE20: =AVERAGE(S20:AD20) -> 83.836599
A21: Total Fixed assets | D21: =D23+D22 -> 2750 | E21: =E23+E22 -> 2616 | F21: =F23+F22 -> 2597 | G21: =G23+G22 -> 2484 | H21: =H23+H22 -> 2366 | I21: =I23+I22 -> 2218 | J21: =J23+J22 -> 2031 | K21: =K23+K22 -> 1857 | ... U21: =U23+U22 -> 898 | V21: =V19+V20 -> 810.91667 | W21: =W19+W20 -> 744.82152 | X21: =X19+X20 -> 693.58433 | Y21: =Y19+Y20 -> 652.00149 | Z21: =Z19+Z20 -> 622.52866 | AA21: =AA19+AA20 -> 603.73401 | AB21: =AB19+AB20 -> 594.11566 | AC21: =AC19+AC20 -> 588.50469 | ... AE21: =AE19+AE20 -> 571.93853
A22: Less: Amortization | D22: ='Cash Flow Statement'!B54 -> 137 | E22: ='Cash Flow Statement'!C54 -> 138 | F22: ='Cash Flow Statement'!D54 -> 143 | G22: ='Cash Flow Statement'!E54 -> 145 | H22: ='Cash Flow Statement'!F54 -> 155 | I22: ='Cash Flow Statement'!G54 -> 182 | J22: ='Cash Flow Statement'!H54 -> 181 | K22: ='Cash Flow Statement'!I54 -> 181 | ... U22: ='Cash Flow Statement'!S54 -> 143 | V22: =V21*V25 -> 127.08821 | W22: =W21*W25 -> 116.72966 | X22: =X21*X25 -> 108.69969 | Y22: =Y21*Y25 -> 102.18276 | Z22: =Z21*Z25 -> 97.563724 | AA22: =AA21*AA25 -> 94.618196 | AB22: =AB21*AB25 -> 93.110791 | AC22: =AC21*AC25 -> 92.231431 | ... AE22: =AE21*AE25 -> 89.635155
A23: Closing balance | C23: ='Balance Sheet'!B20 -> 2737 | D23: ='Balance Sheet'!C20 -> 2613 | E23: ='Balance Sheet'!D20 -> 2478 | F23: ='Balance Sheet'!E20 -> 2454 | G23: ='Balance Sheet'!F20 -> 2339 | H23: ='Balance Sheet'!G20 -> 2211 | I23: ='Balance Sheet'!H20 -> 2036 | J23: ='Balance Sheet'!I20 -> 1850 | ... U23: ='Balance Sheet'!T20 -> 755 | V23: =V21-V22 -> 683.82846 | W23: =W21-W22 -> 628.09185 | X23: =X21-X22 -> 584.88464 | Y23: =Y21-Y22 -> 549.81874 | Z23: =Z21-Z22 -> 524.96493 | AA23: =AA21-AA22 -> 509.11582 | AB23: =AB21-AB22 -> 501.00486 | AC23: =AC21-AC22 -> 496.27326 | ... AE23: =AE21-AE22 -> 482.30337
A25: Rate of amortization | D25: =D22/D21 -> 0.049818182 | E25: =E22/E21 -> 0.052752294 | F25: =F22/F21 -> 0.055063535 | G25: =G22/G21 -> 0.058373591 | H25: =H22/H21 -> 0.065511412 | I25: =I22/I21 -> 0.082055906 | J25: =J22/J21 -> 0.089118661 | K25: =K22/K21 -> 0.097469036 | ... U25: =U22/U21 -> 0.15924276 | V25: =AVERAGE($S25:$U25) -> 0.15672166 | W25: =AVERAGE($S25:$U25) -> 0.15672166 | X25: =AVERAGE($S25:$U25) -> 0.15672166 | Y25: =AVERAGE($S25:$U25) -> 0.15672166 | Z25: =AVERAGE($S25:$U25) -> 0.15672166 | AA25: =AVERAGE($S25:$U25) -> 0.15672166 | AB25: =AVERAGE($S25:$U25) -> 0.15672166 | AC25: =AVERAGE($S25:$U25) -> 0.15672166 | ... AE25: =AVERAGE($S25:$U25) -> 0.15672166

Sheet WACC
A2: WACC (Working Average Cost of Capital)
B5: WACC = (% Equity × Cost of Equity) + (% Debt × Cost of Debt × (1 – Tax Rate))
B6: Cost of Equity = Risk-Free Rate + Company Beta × (Market Return – Risk-Free Rate)
B8: WACC (November 12, 2025)
B9: Market cap | F9: 4850000
B10: % | F10: =F9/(F16+F9) -> 0.99799188
B11: Cost of equity | F11: =F12+F13*F14 -> 0.1027
B12: Risk Free rate | F12: 0.0415
B13: Beta | F13: 1.2
B14: Market Risk Premium | F14: 0.051
B16: Debt | F16: =N41 -> 9759
B17: % | F17: =F16/(F9+F16) -> 0.0020081243
B18: Cost of debt | F18: 0.039
B19: Tax Rate | F19: 0.17
B21: WACC | F21: =F10*F11+F17*F18*(1-F19) -> 0.10255877
D24: Risk-Free Rate | E24: Cost of Equity | F24: Cost of Debt (After tax) | G24: (Adjusted) BETA | H24: Equity Risk Premium | I24: WACC
B25: Alphaspread | D25: 0.0409 | E25: 0.0912 | F25: 0.0511 | G25: 1.22 | H25: 0.0412 | I25: 0.0911
B26: ValueInvesting | D26: 0.0415 | E26: 0.111 | F26: 0.0425 | G26: 1.11 | H26: 0.051 | I26: 0.097
K31: Loan | L31: Expected Remaining Term (years) | M31: Effective Interest Rate | N31: Notional Value | O31: Annual Interest
K32: Note 2024 | L32: 0.4 | M32: 0.0066 | N32: 1250 | O32: =N32*M32 -> 8.25
K33: Note 2026 | L33: 2.6 | M33: 0.0331 | N33: 1000 | O33: =N33*M33 -> 33.1
K34: Note 2028 | L34: 4.4 | M34: 0.0164 | N34: 1250 | O34: =N34*M34 -> 20.5
K35: Note 2030 | L35: 6.2 | M35: 0.0293 | N35: 1500 | O35: =N35*M35 -> 43.95
K36: Note 2031 | L36: 7.4 | M36: 0.0209 | N36: 1250 | O36: =N36*M36 -> 26.125
K37: Note 2040 | L37: 16.2 | M37: 0.0354 | N37: 1000 | O37: =N37*M37 -> 35.4
K38: Note 2050 | L38: 26.2 | M38: 0.0354 | N38: 2000 | O38: =N38*M38 -> 70.8
K39: Note 2060 | L39: 36.2 | M39: 0.0373 | N39: 509 | O39: =N39*M39 -> 18.9857
N41: =SUM(N32:N39) -> 9759 | O41: =SUM(O32:O39) -> 257.1107 | P41: =O41/N41 -> 0.026346009

Sheet DCF Valuation
A2: Discounted Cash Flow
B4: Ticker | D4: NVDA | F4: Implied share price (Nov 12, 2025) | J4: =E88 -> 739.15195
B5: Date | D5: 45973 | F5: Current share price (Nov 12, 2025) | J5: 193.16
B6: Year Start | D6: 45684 | F6: Implied Gain/Loss | J6: =J4/J5-1 -> 2.8266305
B7: Year End | D7: 46047
A9: x | B9: Income Statement (End of January YE) | F9: Q1 2022 | G9: =IF(MID(F9,2,1)="4","Q1 "&RIGHT(F9,4)+1, "Q"&MID(F9,2,1)+1&" "&RIGHT(F9,4)) -> Q2 2022 | H9: =IF(MID(G9,2,1)="4","Q1 "&RIGHT(G9,4)+1, "Q"&MID(G9,2,1)+1&" "&RIGHT(G9,4)) -> Q3 2022 | I9: =IF(MID(H9,2,1)="4","Q1 "&RIGHT(H9,4)+1, "Q"&MID(H9,2,1)+1&" "&RIGHT(H9,4)) -> Q4 2022 | J9: =IF(MID(I9,2,1)="4","Q1 "&RIGHT(I9,4)+1, "Q"&MID(I9,2,1)+1&" "&RIGHT(I9,4)) -> Q1 2023 | K9: =IF(MID(J9,2,1)="4","Q1 "&RIGHT(J9,4)+1, "Q"&MID(J9,2,1)+1&" "&RIGHT(J9,4)) -> Q2 2023 | L9: =IF(MID(K9,2,1)="4","Q1 "&RIGHT(K9,4)+1, "Q"&MID(K9,2,1)+1&" "&RIGHT(K9,4)) -> Q3 2023 | M9: =IF(MID(L9,2,1)="4","Q1 "&RIGHT(L9,4)+1, "Q"&MID(L9,2,1)+1&" "&RIGHT(L9,4)) -> Q4 2023 | N9: =IF(MID(M9,2,1)="4","Q1 "&RIGHT(M9,4)+1, "Q"&MID(M9,2,1)+1&" "&RIGHT(M9,4)) -> Q1 2024 | ... AG9: =IF(MID(AF9,2,1)="4","Q1 "&RIGHT(AF9,4)+1, "Q"&MID(AF9,2,1)+1&" "&RIGHT(AF9,4)) -> Q4 2028 | AH9: 2029 | AI9: 2030
B10: Revenue | F10: ='Income Statement'!C9 -> 5,661 | G10: ='Income Statement'!D9 -> 6,507 | H10: ='Income Statement'!E9 -> 7103 | I10: ='Income Statement'!F9 -> 7643 | J10: ='Income Statement'!G9 -> 8288 | K10: ='Income Statement'!H9 -> 6,704 | L10: ='Income Statement'!I9 -> 5,931 | M10: ='Income Statement'!J9 -> 6051 | ... W10: ='Income Statement'!T9 -> 46743 | X10: 47435 | Y10: 48069 | Z10: 56242 | AA10: 65803 | AB10: 77990 | AC10: 91843 | AD10: 112893 | AE10: 139267 | AF10: 171807 | AG10: 211317 | AH10: 259922 | AI10: 319700
B11: % growth | G11: =G10/F10-1 -> 0.14944356 | H11: =H10/G10-1 -> 0.091593668 | I11: =I10/H10-1 -> 0.076024215 | J11: =J10/I10-1 -> 0.084390946 | K11: =K10/J10-1 -> -0.19111969 | L11: =L10/K10-1 -> -0.1153043 | M11: =M10/L10-1 -> 0.020232676 | N11: =N10/M10-1 -> 0.18856387 | ... AI11: =AI10/AH10-1 -> 0.22998438
B13: Gross Profit | F13: ='Income Statement'!C11 -> 3,629 | G13: ='Income Statement'!D11 -> 4,215 | H13: ='Income Statement'!E11 -> 4,631 | I13: ='Income Statement'!F11 -> 5000 | J13: ='Income Statement'!G11 -> 5431 | K13: ='Income Statement'!H11 -> 2,915 | L13: ='Income Statement'!I11 -> 3,177 | M13: ='Income Statement'!J11 -> 3833 | ... W13: ='Income Statement'!T11 -> 33853 | X13: =X10*X14 -> 36192.905 | Y13: =Y10*Y14 -> 33712.37 | Z13: =Z10*Z14 -> 39689.472 | AA13: =AA10*AA14 -> 45960.232 | AB13: =AB10*AB14 -> 56430.847 | AC13: =AC10*AC14 -> 65862.355 | AD13: =AD10*AD14 -> 79844.73 | AE13: =AE10*AE14 -> 99047.631 | ... AI13: =AI10*AI14 -> 227374.94
B14: % of revenue | F14: =F13/F$10 -> 0.64105282 | G14: =G13/G$10 -> 0.64776395 | H14: =H13/H$10 -> 0.65197804 | I14: =I13/I$10 -> 0.65419338 | J14: =J13/J$10 -> 0.65528475 | K14: =K13/K$10 -> 0.43481504 | L14: =L13/L$10 -> 0.53566009 | M14: =M13/M$10 -> 0.63344902 | ... W14: =W13/W$10 -> 0.72423678 | X14: 0.763 | Y14: =AVERAGE(T14:W14) -> 0.70133287 | Z14: =AVERAGE(U14:X14) -> 0.70569099 | AA14: =AVERAGE(V14:Y14) -> 0.69845193 | AB14: =AVERAGE(W14:Z14) -> 0.72356516 | AC14: =AVERAGE(X14:AA14) -> 0.71711895 | AD14: =AVERAGE(Y14:AB14) -> 0.70726024 | AE14: =AVERAGE(Z14:AC14) -> 0.71120676 | AF14: =AVERAGE(AA14:AD14) -> 0.71159907 | ... AI14: =AVERAGE(AD14:AG14) -> 0.71121346
B16: EBIT | F16: ='Income Statement'!C19+'Income Statement'!C20+'Income Statement'!C21 -> 1909 | G16: ='Income Statement'!D19+'Income Statement'!D20+'Income Statement'!D21 -> 2390 | H16: ='Income Statement'!E19+'Income Statement'!E20+'Income Statement'!E21 -> 2616 | I16: ='Income Statement'!F19+'Income Statement'!F20+'Income Statement'!F21 -> 2919 | J16: ='Income Statement'!G19+'Income Statement'!G20+'Income Statement'!G21 -> 1818 | K16: ='Income Statement'!H19+'Income Statement'!H20+'Income Statement'!H21 -> 480 | L16: ='Income Statement'!I19+'Income Statement'!I20+'Income Statement'!I21 -> 624 | M16: ='Income Statement'!J19+'Income Statement'!J20+'Income Statement'!J21 -> 1307 | ... W16: ='Income Statement'!T19+'Income Statement'!T20+'Income Statement'!T21 -> 28970 | X16: =X13-3500 -> 32692.905 | Y16: =Y13-3500 -> 30212.37 | Z16: =Z13-3500 -> 36189.472 | AA16: =AA13-3500 -> 42460.232 | AB16: =AB13-3500 -> 52930.847 | AC16: =AC13-3500 -> 62362.355 | AD16: =AD13-3500 -> 76344.73 | AE16: =AE13-3500 -> 95547.631 | ... AI16: =AI13-3500 -> 223874.94
B17: % of revenue | F17: =F16/F$10 -> 0.33721957 | G17: =G16/G$10 -> 0.36729676 | H17: =H16/H$10 -> 0.36829509 | I17: =I16/I$10 -> 0.38191809 | J17: =J16/J$10 -> 0.21935328 | K17: =K16/K$10 -> 0.071599045 | L17: =L16/L$10 -> 0.10520991 | M17: =M16/M$10 -> 0.21599736 | ... X17: =X16/X$10 -> 0.68921482 | Y17: =Y16/Y10 -> 0.62852087 | Z17: =Z16/Z10 -> 0.64345991 | AA17: =AA16/AA10 -> 0.64526287 | AB17: =AB16/AB10 -> 0.67868761 | AC17: =AC16/AC10 -> 0.67901043 | AD17: =AD16/AD10 -> 0.67625743 | AE17: =AE16/AE10 -> 0.68607517 | AF17: =AF16/AF10 -> 0.69122737 | ... AI17: =AI16/AI10 -> 0.70026569
B19: Taxes | F19: ='Income Statement'!C26 -> 132 | G19: ='Income Statement'!D26 -> 20 | H19: ='Income Statement'!E26 -> 174 | I19: ='Income Statement'!F26 -> -137 | J19: ='Income Statement'!G26 -> 187 | K19: ='Income Statement'!H26 -> (181) | L19: ='Income Statement'!I26 -> (67) | M19: ='Income Statement'!J26 -> -126 | ... W19: ='Income Statement'!T26 -> 4784 | X19: =X16*X20 -> 5557.7939 | Y19: =Y16*Y20 -> 5136.1028 | Z19: =Z16*Z20 -> 6152.2103 | AA19: =AA16*AA20 -> 7218.2395 | AB19: =AB16*AB20 -> 8998.244 | AC19: =AC16*AC20 -> 10601.6 | AD19: =AD16*AD20 -> 12978.604 | AE19: =AE16*AE20 -> 16243.097 | ... AI19: =AI16*AI20 -> 38058.74
B20: % of EBIT | F20: =F19/'Income Statement'!C25 -> 0.064579256 | G20: =G19/'Income Statement'!D25 -> 0.0083542189 | H20: =H19/'Income Statement'!E25 -> 0.06595906 | I20: =I19/'Income Statement'!F25 -> -0.047818499 | J20: =J19/'Income Statement'!G25 -> 0.10360111 | K20: =K19/'Income Statement'!H25 -> -0.38105263 | L20: =L19/'Income Statement'!I25 -> -0.10929853 | M20: =M19/'Income Statement'!J25 -> -0.097826087 | ... W20: =W19/'Income Statement'!T25 -> 0.15330385 | X20: 0.17 | Y20: 0.17 | Z20: 0.17 | AA20: 0.17 | AB20: 0.17 | AC20: 0.17 | AD20: 0.17 | AE20: 0.17 | AF20: 0.17 | AG20: 0.17 | AH20: 0.17 | AI20: 0.17
A22: x | B22: Cash Flow Items | F22: Q1 2022 | G22: =IF(MID(F22,2,1)="4","Q1 "&RIGHT(F22,4)+1, "Q"&MID(F22,2,1)+1&" "&RIGHT(F22,4)) -> Q2 2022 | H22: =IF(MID(G22,2,1)="4","Q1 "&RIGHT(G22,4)+1, "Q"&MID(G22,2,1)+1&" "&RIGHT(G22,4)) -> Q3 2022 | I22: =IF(MID(H22,2,1)="4","Q1 "&RIGHT(H22,4)+1, "Q"&MID(H22,2,1)+1&" "&RIGHT(H22,4)) -> Q4 2022 | J22: =IF(MID(I22,2,1)="4","Q1 "&RIGHT(I22,4)+1, "Q"&MID(I22,2,1)+1&" "&RIGHT(I22,4)) -> Q1 2023 | K22: =IF(MID(J22,2,1)="4","Q1 "&RIGHT(J22,4)+1, "Q"&MID(J22,2,1)+1&" "&RIGHT(J22,4)) -> Q2 2023 | L22: =IF(MID(K22,2,1)="4","Q1 "&RIGHT(K22,4)+1, "Q"&MID(K22,2,1)+1&" "&RIGHT(K22,4)) -> Q3 2023 | M22: =IF(MID(L22,2,1)="4","Q1 "&RIGHT(L22,4)+1, "Q"&MID(L22,2,1)+1&" "&RIGHT(L22,4)) -> Q4 2023 | N22: =IF(MID(M22,2,1)="4","Q1 "&RIGHT(M22,4)+1, "Q"&MID(M22,2,1)+1&" "&RIGHT(M22,4)) -> Q1 2024 | ... AG22: =IF(MID(AF22,2,1)="4","Q1 "&RIGHT(AF22,4)+1, "Q"&MID(AF22,2,1)+1&" "&RIGHT(AF22,4)) -> Q4 2028 | AH22: 2029 | AI22: 2030
B23: D&A | F23: ='Cash Flow Statement'!B14 -> 281 | G23: ='Cash Flow Statement'!C14-'Cash Flow Statement'!B14 -> 286 | H23: ='Cash Flow Statement'!D14-'Cash Flow Statement'!C14 -> 298 | I23: ='Cash Flow Statement'!E14-'Cash Flow Statement'!D14 -> 309 | J23: ='Cash Flow Statement'!F14 -> 334 | K23: ='Cash Flow Statement'!G14-'Cash Flow Statement'!F14 -> 378 | L23: ='Cash Flow Statement'!H14-'Cash Flow Statement'!G14 -> 406 | M23: ='Cash Flow Statement'!I14-'Cash Flow Statement'!H14 -> 426 | N23: ='Cash Flow Statement'!J14 -> 384 | O23: ='Cash Flow Statement'!K14-'Cash Flow Statement'!J14 -> 365 | P23: ='Cash Flow Statement'!L14-'Cash Flow Statement'!K14 -> 372 | Q23: ='Cash Flow Statement'!M14-'Cash Flow Statement'!L14 -> 387 | R23: ='Cash Flow Statement'!N14-'Cash Flow Statement'!M14 -> -1098 | S23: ='Cash Flow Statement'!O14-'Cash Flow Statement'!N14 -> 433 | T23: ='Cash Flow Statement'!P14-'Cash Flow Statement'!O14 -> 478 | U23: ='Cash Flow Statement'!Q14-'Cash Flow Statement'!P14 -> 543 | V23: ='Cash Flow Statement'!R14-'Cash Flow Statement'!Q14 -> -1253 | W23: ='Cash Flow Statement'!S14-'Cash Flow Statement'!R14 -> 669 | X23: =X24+X25 -> -1098 | Y23: =Y24+Y25 -> 433 | Z23: =Z24+Z25 -> 478 | AA23: =AA24+AA25 -> 543 | AB23: =AB24+AB25 -> -1253 | AC23: =AC24+AC25 -> 669 | AD23: =AD24+AD25 -> -180.09338 | AE23: =AE24+AE25 -> -194.5576 | ... AG23: =AG24+AG25 -> -323.9471 | AH23: -1175 | AI23: -1446
B24: Depreciation | F24: =F23-F25 -> 144 | G24: =G23-G25 -> 148 | H24: =H23-H25 -> 155 | I24: =I23-I25 -> 164 | J24: =J23-J25 -> 179 | K24: =K23-K25 -> 196 | L24: =L23-L25 -> 225 | M24: =M23-M25 -> 245 | ... W24: =W23-W25 -> 526 | X24: ='Fixed Assets'!P11 -> -1279 | Y24: ='Fixed Assets'!Q11 -> 252 | Z24: ='Fixed Assets'!R11 -> 297 | AA24: ='Fixed Assets'!S11 -> 397 | AB24: ='Fixed Assets'!T11 -> -1397 | AC24: ='Fixed Assets'!U11 -> 526 | AD24: ='Fixed Assets'!V11 -> -307.18158 | AE24: ='Fixed Assets'!W11 -> -311.28727 | ... AI24: ='Fixed Assets'!AA11 -> -594.76079
B25: Amortization | F25: ='Cash Flow Statement'!B54 -> 137 | G25: ='Cash Flow Statement'!C54 -> 138 | H25: ='Cash Flow Statement'!D54 -> 143 | I25: ='Cash Flow Statement'!E54 -> 145 | J25: ='Cash Flow Statement'!F54 -> 155 | K25: ='Cash Flow Statement'!G54 -> 182 | L25: ='Cash Flow Statement'!H54 -> 181 | M25: ='Cash Flow Statement'!I54 -> 181 | ... W25: ='Cash Flow Statement'!S54 -> 143 | X25: ='Fixed Assets'!P22 -> 181 | Y25: ='Fixed Assets'!Q22 -> 181 | Z25: ='Fixed Assets'!R22 -> 181 | AA25: ='Fixed Assets'!S22 -> 146 | AB25: ='Fixed Assets'!T22 -> 144 | AC25: ='Fixed Assets'!U22 -> 143 | AD25: ='Fixed Assets'!V22 -> 127.08821 | AE25: ='Fixed Assets'!W22 -> 116.72966 | ... AI25: ='Fixed Assets'!AA22 -> 94.618196
B26: % of revenue | F26: =F23/F$10 -> 0.049637873 | G26: =G23/G$10 -> 0.043952666 | H26: =H23/H$10 -> 0.041954104 | I26: =I23/I$10 -> 0.040429151 | J26: =J23/J$10 -> 0.040299228 | K26: =K23/K$10 -> 0.056384248 | L26: =L23/L$10 -> 0.068453886 | M26: =M23/M$10 -> 0.070401587 | ... AI26: =AI23/AI$10 -> -0.0045229903
B28: CapEx | F28: =-1*'Cash Flow Statement'!B31 -> 298 | G28: =('Cash Flow Statement'!C31-'Cash Flow Statement'!B31)*-1 -> 183 | H28: =('Cash Flow Statement'!D31-'Cash Flow Statement'!C31)*-1 -> 222 | I28: =('Cash Flow Statement'!E31-'Cash Flow Statement'!D31)*-1 -> 273 | J28: =-1*'Cash Flow Statement'!F31 -> 361 | K28: =('Cash Flow Statement'!G31-'Cash Flow Statement'!F31)*-1 -> 433 | L28: =('Cash Flow Statement'!H31-'Cash Flow Statement'!G31)*-1 -> 530 | M28: =('Cash Flow Statement'!I31-'Cash Flow Statement'!H31)*-1 -> 509 | N28: =-1*'Cash Flow Statement'!J31 -> 248 | O28: =('Cash Flow Statement'!K31-'Cash Flow Statement'!J31)*-1 -> 289 | P28: =('Cash Flow Statement'!L31-'Cash Flow Statement'!K31)*-1 -> 278 | Q28: =('Cash Flow Statement'!M31-'Cash Flow Statement'!L31)*-1 -> 254 | R28: =('Cash Flow Statement'!N31-'Cash Flow Statement'!M31)*-1 -> -700 | S28: =('Cash Flow Statement'!O31-'Cash Flow Statement'!N31)*-1 -> 977 | T28: =('Cash Flow Statement'!P31-'Cash Flow Statement'!O31)*-1 -> 813 | U28: =('Cash Flow Statement'!Q31-'Cash Flow Statement'!P31)*-1 -> 1077 | V28: =('Cash Flow Statement'!R31-'Cash Flow Statement'!Q31)*-1 -> -2009 | W28: =('Cash Flow Statement'!S31-'Cash Flow Statement'!R31)*-1 -> 1895 | X28: ='Fixed Assets'!P9 -> -1187 | Y28: ='Fixed Assets'!Q9 -> 1131 | Z28: ='Fixed Assets'!R9 -> 755 | AA28: ='Fixed Assets'!S9 -> 1337 | AB28: ='Fixed Assets'!T9 -> -544 | AC28: ='Fixed Assets'!U9 -> 2531 | AD28: ='Fixed Assets'!V9 -> -2029.1708 | AE28: ='Fixed Assets'!W9 -> -212.1273 | ... AG28: ='Fixed Assets'!Y9 -> 1069.2462 | AH28: 4159 | AI28: 5115
B29: % of revenue | F29: =F28/F$10 -> 0.052640876 | G29: =G28/G$10 -> 0.028123559 | H29: =H28/H$10 -> 0.0312544 | I29: =I28/I$10 -> 0.035718959 | J29: =J28/J$10 -> 0.04355695 | K29: =K28/K$10 -> 0.064588305 | L29: =L28/L$10 -> 0.089360985 | M29: =M28/M$10 -> 0.084118328 | ... AI29: =AI28/AI$10 -> 0.015999374
Z30: =SUM(X28:AA28) -> 2036
B31: Change in NWC | F31: ='Working Capital'!E18 -> 887 | G31: ='Working Capital'!F18 -> 249 | H31: ='Working Capital'!G18 -> 192 | I31: ='Working Capital'!H18 -> 390 | J31: ='Working Capital'!I18 -> 389 | K31: ='Working Capital'!J18 -> 382 | L31: ='Working Capital'!K18 -> 417 | M31: ='Working Capital'!L18 -> -10 | ... AG31: ='Working Capital'!AF18 -> 27169.625 | AH31: 21313 | AI31: 26215
B32: % of revenue | F32: =F31/F$10 -> 0.1566861 | G32: =G31/G$10 -> 0.038266482 | H32: =H31/H$10 -> 0.027030832 | I32: =I31/I$10 -> 0.051027084 | J32: =J31/J$10 -> 0.046935328 | K32: =K31/K$10 -> 0.056980907 | L32: =L31/L$10 -> 0.070308548 | M32: =M31/M$10 -> -0.0016526194 | ... AI32: =AI31/AI$10 -> 0.081998749
B33: % of change in revenue | G33: =G31/(G10-F10) -> 0.29432624 | H33: =H31/(H10-G10) -> 0.32214765 | I33: =I31/(I10-H10) -> 0.72222222 | J33: =J31/(J10-I10) -> 0.60310078 | K33: =K31/(K10-J10) -> -0.24116162 | L33: =L31/(L10-K10) -> -0.53945666 | M33: =M31/(M10-L10) -> -0.083333333 | N33: =N31/(N10-M10) -> -0.79842244 | ... AI33: =AI31/(AI10-AH10) -> 0.43853926
B35: Assumptions | F35: Q1 2022 | G35: =IF(MID(F35,2,1)="4","Q1 "&RIGHT(F35,4)+1, "Q"&MID(F35,2,1)+1&" "&RIGHT(F35,4)) -> Q2 2022 | H35: =IF(MID(G35,2,1)="4","Q1 "&RIGHT(G35,4)+1, "Q"&MID(G35,2,1)+1&" "&RIGHT(G35,4)) -> Q3 2022 | I35: =IF(MID(H35,2,1)="4","Q1 "&RIGHT(H35,4)+1, "Q"&MID(H35,2,1)+1&" "&RIGHT(H35,4)) -> Q4 2022 | J35: =IF(MID(I35,2,1)="4","Q1 "&RIGHT(I35,4)+1, "Q"&MID(I35,2,1)+1&" "&RIGHT(I35,4)) -> Q1 2023 | K35: =IF(MID(J35,2,1)="4","Q1 "&RIGHT(J35,4)+1, "Q"&MID(J35,2,1)+1&" "&RIGHT(J35,4)) -> Q2 2023 | L35: =IF(MID(K35,2,1)="4","Q1 "&RIGHT(K35,4)+1, "Q"&MID(K35,2,1)+1&" "&RIGHT(K35,4)) -> Q3 2023 | M35: =IF(MID(L35,2,1)="4","Q1 "&RIGHT(L35,4)+1, "Q"&MID(L35,2,1)+1&" "&RIGHT(L35,4)) -> Q4 2023 | N35: =IF(MID(M35,2,1)="4","Q1 "&RIGHT(M35,4)+1, "Q"&MID(M35,2,1)+1&" "&RIGHT(M35,4)) -> Q1 2024 | ... W35: =IF(MID(V35,2,1)="4","Q1 "&RIGHT(V35,4)+1, "Q"&MID(V35,2,1)+1&" "&RIGHT(V35,4)) -> Q2 2026
B36: Scenarios | F36: Scenario 1 - Conservative | K36: Scenario 2 - Base | O36: Scenario 3 - Optimistic
A37: x | B37: Revenue | D37: 2 | F37: Revenue Growth FY27 | I37: 0.35 | O37: Revenue Growth FY27 | R37: 0.9
B38: EBIT | D38: 2 | F38: Revenue Q4 '28 | I38: 0.08 | K38: Revenue Q4 '28 | M38: 0.1 | O38: Revenue Q4 '28 | R38: 0.146
B39: WACC | D39: 2 | F39: EBIT Margin FY28 | I39: 0.4 | O39: EBIT Margin FY28 | R39: 0.57
B40: g | D40: 2 | K40: Taxes | M40: 0.17
B42: WACC | D42: =CHOOSE(D39,I42,M42,R42) -> 0.10255877 | F42: WACC | I42: =M42+0.01 -> 0.11255877 | K42: WACC | M42: =WACC!F21 -> 0.10255877 | O42: WACC | R42: =M42-0.01 -> 0.092558769
B43: g | D43: =CHOOSE(D40,I43,M43,R43) -> 0.035 | F43: g | I43: 0.03 | K43: g | M43: 0.035 | O43: g | R43: 0.04
B47: Discounted Cash Flow | F47: Q1 2022 | G47: =IF(MID(F47,2,1)="4","Q1 "&RIGHT(F47,4)+1, "Q"&MID(F47,2,1)+1&" "&RIGHT(F47,4)) -> Q2 2022 | H47: =IF(MID(G47,2,1)="4","Q1 "&RIGHT(G47,4)+1, "Q"&MID(G47,2,1)+1&" "&RIGHT(G47,4)) -> Q3 2022 | I47: =IF(MID(H47,2,1)="4","Q1 "&RIGHT(H47,4)+1, "Q"&MID(H47,2,1)+1&" "&RIGHT(H47,4)) -> Q4 2022 | J47: =IF(MID(I47,2,1)="4","Q1 "&RIGHT(I47,4)+1, "Q"&MID(I47,2,1)+1&" "&RIGHT(I47,4)) -> Q1 2023 | K47: =IF(MID(J47,2,1)="4","Q1 "&RIGHT(J47,4)+1, "Q"&MID(J47,2,1)+1&" "&RIGHT(J47,4)) -> Q2 2023 | L47: =IF(MID(K47,2,1)="4","Q1 "&RIGHT(K47,4)+1, "Q"&MID(K47,2,1)+1&" "&RIGHT(K47,4)) -> Q3 2023 | M47: =IF(MID(L47,2,1)="4","Q1 "&RIGHT(L47,4)+1, "Q"&MID(L47,2,1)+1&" "&RIGHT(L47,4)) -> Q4 2023 | N47: =IF(MID(M47,2,1)="4","Q1 "&RIGHT(M47,4)+1, "Q"&MID(M47,2,1)+1&" "&RIGHT(M47,4)) -> Q1 2024 | ... W47: =IF(MID(V47,2,1)="4","Q1 "&RIGHT(V47,4)+1, "Q"&MID(V47,2,1)+1&" "&RIGHT(V47,4)) -> Q2 2026 | X47: =IF(MID(W35,2,1)="4","Q1 "&RIGHT(W35,4)+1, "Q"&MID(W35,2,1)+1&" "&RIGHT(W35,4)) -> Q3 2026 | Y47: =IF(MID(X47,2,1)="4","Q1 "&RIGHT(X47,4)+1, "Q"&MID(X47,2,1)+1&" "&RIGHT(X47,4)) -> Q4 2026 | Z47: =IF(MID(Y47,2,1)="4","Q1 "&RIGHT(Y47,4)+1, "Q"&MID(Y47,2,1)+1&" "&RIGHT(Y47,4)) -> Q1 2027 | AA47: =IF(MID(Z47,2,1)="4","Q1 "&RIGHT(Z47,4)+1, "Q"&MID(Z47,2,1)+1&" "&RIGHT(Z47,4)) -> Q2 2027 | AB47: =IF(MID(AA47,2,1)="4","Q1 "&RIGHT(AA47,4)+1, "Q"&MID(AA47,2,1)+1&" "&RIGHT(AA47,4)) -> Q3 2027 | AC47: =IF(MID(AB47,2,1)="4","Q1 "&RIGHT(AB47,4)+1, "Q"&MID(AB47,2,1)+1&" "&RIGHT(AB47,4)) -> Q4 2027 | AD47: =IF(MID(AC47,2,1)="4","Q1 "&RIGHT(AC47,4)+1, "Q"&MID(AC47,2,1)+1&" "&RIGHT(AC47,4)) -> Q1 2028 | AE47: =IF(MID(AD47,2,1)="4","Q1 "&RIGHT(AD47,4)+1, "Q"&MID(AD47,2,1)+1&" "&RIGHT(AD47,4)) -> Q2 2028 | AF47: =IF(MID(AE47,2,1)="4","Q1 "&RIGHT(AE47,4)+1, "Q"&MID(AE47,2,1)+1&" "&RIGHT(AE47,4)) -> Q3 2028 | AG47: =IF(MID(AF47,2,1)="4","Q1 "&RIGHT(AF47,4)+1, "Q"&MID(AF47,2,1)+1&" "&RIGHT(AF47,4)) -> Q4 2028 | AH47: 2029 | AI47: 2030
B48: Revenue | F48: =F10 -> 5,661 | G48: =G10 -> 6,507 | H48: =H10 -> 7103 | I48: =I10 -> 7643 | J48: =J10 -> 8288 | K48: =K10 -> 6,704 | L48: =L10 -> 5,931 | M48: =M10 -> 6051 | ... W48: =W10 -> 46743 | X48: =W48*(1+X49) -> 51065.612 | Y48: =X48*(1+Y49) -> 55195.779 | Z48: =Y48*(1+Z49) -> 60239.531 | AA48: =Z48*(1+AA49) -> 64481.781 | AB48: =AA48*(1+AB49) -> 63741.608 | AC48: =AB48*(1+AC49) -> 68779.721 | AD48: =AC48*(1+AD49) -> 70894.502 | AE48: =AD48*(1+AE49) -> 73009.282 | ... AG48: =AF48*(1+AG49) -> 93130.109 | AH48: 259922 | AI48: 319700
A49: x | B49: % growth | G49: =G11 -> 0.14944356 | H49: =H11 -> 0.091593668 | I49: =I11 -> 0.076024215 | J49: =J11 -> 0.084390946 | K49: =K11 -> -0.19111969 | L49: =L11 -> -0.1153043 | M49: =M11 -> 0.020232676 | N49: =N11 -> 0.18856387 | ... W49: =W11 -> 0.060846081 | X49: =OFFSET(X49,$D$37,0) -> 0.092476134 | Y49: =OFFSET(Y49,$D$37,0) -> 0.080879612 | Z49: =OFFSET(Z49,$D$37,0) -> 0.09137931 | AA49: =OFFSET(AA49,$D$37,0) -> 0.07042303 | AB49: =OFFSET(AB49,$D$37,0) -> -0.011478797 | AC49: =OFFSET(AC49,$D$37,0) -> 0.079039625 | AD49: =OFFSET(AD49,$D$37,0) -> 0.030747156 | AE49: =OFFSET(AE49,$D$37,0) -> 0.029829969 | ... AI49: =OFFSET(AI49,$D$37,0) -> 0.12525055
B50: Conservative | X50: 0.092476134 | Y50: =Y51*$I$37 -> 0.028307864 | Z50: =Z51*$I$37 -> 0.031982759 | AA50: =AA51*$I$37 -> 0.02464806 | AB50: =AB51*$I$37 -> -0.004017579 | AC50: =AC51*$I$37 -> 0.027663869 | AD50: =AD51*$I$37 -> 0.010761505 | AE50: =AE51*$I$37 -> 0.010440489 | AF50: =AF51*$I$37 -> 0.046762706 | ... AI50: =AI51*$I$37 -> 0.043837692
B51: Base | X51: 0.092476134 | Y51: 0.080879612 | Z51: 0.09137931 | AA51: 0.07042303 | AB51: -0.011478797 | AC51: 0.079039625 | AD51: 0.030747156 | AE51: 0.029829969 | AF51: 0.13360773 | AG51: 0.12525055 | AH51: 0.12525055 | AI51: 0.12525055
B52: Optimistic | X52: 0.092476134 | Y52: =Y51*$R$37 -> 0.072791651 | Z52: =Z51*$R$37 -> 0.082241379 | AA52: =AA51*$R$37 -> 0.063380727 | AB52: =AB51*$R$37 -> -0.010330917 | AC52: =AC51*$R$37 -> 0.071135662 | AD52: =AD51*$R$37 -> 0.02767244 | AE52: =AE51*$R$37 -> 0.026846972 | AF52: =AF51*$R$37 -> 0.12024696 | ... AI52: =AI51*$R$37 -> 0.11272549
B54: EBIT | F54: =F16 -> 1909 | G54: =G16 -> 2390 | H54: =H16 -> 2616 | I54: =I16 -> 2919 | J54: =J16 -> 1818 | K54: =K16 -> 480 | L54: =L16 -> 624 | M54: =M16 -> 1307 | ... W54: =W16 -> 28970 | X54: =X48*X55 -> 31561.329 | Y54: =Y48*Y55 -> 36213.506 | Z54: =Z48*Z55 -> 39470.269 | AA54: =AA48*AA55 -> 42198.336 | AB54: =AB48*AB55 -> 41644.263 | AC54: =AC48*AC55 -> 44404.757 | AD54: =AD48*AD55 -> 45885.104 | AE54: =AE48*AE55 -> 47365.45 | ... AI54: =AI48*AI55 -> 193360.84
B55: % of revenue | F55: =F17 -> 0.33721957 | G55: =G17 -> 0.36729676 | H55: =H17 -> 0.36829509 | I55: =I17 -> 0.38191809 | J55: =J17 -> 0.21935328 | K55: =K17 -> 0.071599045 | L55: =L17 -> 0.10520991 | M55: =M17 -> 0.21599736 | ... W55: =W17 -> 0.61977194 | X55: =OFFSET(X55,$D$38,0) -> 0.61805446 | Y55: =OFFSET(Y55,$D$38,0) -> 0.65609195 | Z55: =OFFSET(Z55,$D$38,0) -> 0.65522205 | AA55: =OFFSET(AA55,$D$38,0) -> 0.65442262 | AB55: =OFFSET(AB55,$D$38,0) -> 0.65332935 | AC55: =OFFSET(AC55,$D$38,0) -> 0.64560828 | AD55: =OFFSET(AD55,$D$38,0) -> 0.64723078 | AE55: =OFFSET(AE55,$D$38,0) -> 0.64875929 | ... AI55: =OFFSET(AI55,$D$38,0) -> 0.60481965
B56: Conservative | X56: 0.61805446 | Y56: =Y57*$I$39 -> 0.26243678 | Z56: =Z57*$I$39 -> 0.26208882 | AA56: =AA57*$I$39 -> 0.26176905 | AB56: =AB57*$I$39 -> 0.26133174 | AC56: =AC57*$I$39 -> 0.25824331 | AD56: =AD57*$I$39 -> 0.25889231 | AE56: =AE57*$I$39 -> 0.25950372 | AF56: =AF57*$I$39 -> 0.25346246 | ... AI56: =AI57*$I$39 -> 0.24192786
B57: Base | X57: 0.61805446 | Y57: 0.65609195 | Z57: 0.65522205 | AA57: 0.65442262 | AB57: 0.65332935 | AC57: 0.64560828 | AD57: 0.64723078 | AE57: 0.64875929 | AF57: 0.63365615 | AG57: 0.60481965 | AH57: 0.60481965 | AI57: 0.60481965
B58: Optimistic | X58: 0.61805446 | Y58: =Y57*$R$39 -> 0.37397241 | Z58: =Z57*$R$39 -> 0.37347657 | AA58: =AA57*$R$39 -> 0.37302089 | AB58: =AB57*$R$39 -> 0.37239773 | AC58: =AC57*$R$39 -> 0.36799672 | AD58: =AD57*$R$39 -> 0.36892155 | AE58: =AE57*$R$39 -> 0.3697928 | AF58: =AF57*$R$39 -> 0.36118401 | ... AI58: =AI57*$R$39 -> 0.3447472
B60: Taxes | X60: =X54*X61 -> 5365.426 | Y60: =Y54*Y61 -> 6156.2961 | Z60: =Z54*Z61 -> 6709.9457 | AA60: =AA54*AA61 -> 7173.7171 | AB60: =AB54*AB61 -> 7079.5248 | AC60: =AC54*AC61 -> 7548.8088 | AD60: =AD54*AD61 -> 7800.4677 | AE60: =AE54*AE61 -> 8052.1266 | ... AI60: =AI54*AI61 -> 32871.343
B61: % of EBIT | X61: =$M$40 -> 0.17 | Y61: =$M$40 -> 0.17 | Z61: =$M$40 -> 0.17 | AA61: =$M$40 -> 0.17 | AB61: =$M$40 -> 0.17 | AC61: =$M$40 -> 0.17 | AD61: =$M$40 -> 0.17 | AE61: =$M$40 -> 0.17 | ... AI61: =$M$40 -> 0.17
B63: EBIAT | X63: =X54-X60 -> 26195.903 | Y63: =Y54-Y60 -> 30057.21 | Z63: =Z54-Z60 -> 32760.323 | AA63: =AA54-AA60 -> 35024.619 | AB63: =AB54-AB60 -> 34564.739 | AC63: =AC54-AC60 -> 36855.949 | AD63: =AD54-AD60 -> 38084.636 | AE63: =AE54-AE60 -> 39313.324 | ... AI63: =AI54-AI60 -> 160489.5
B65: D&A | F65: =F23 -> 281 | G65: =G23 -> 286 | H65: =H23 -> 298 | I65: =I23 -> 309 | J65: =J23 -> 334 | K65: =K23 -> 378 | L65: =L23 -> 406 | M65: =M23 -> 426 | ... AI65: =AI23 -> -1446
B66: % of revenue | F66: =F26 -> 0.049637873 | G66: =G26 -> 0.043952666 | H66: =H26 -> 0.041954104 | I66: =I26 -> 0.040429151 | J66: =J26 -> 0.040299228 | K66: =K26 -> 0.056384248 | L66: =L26 -> 0.068453886 | M66: =M26 -> 0.070401587 | ... AI66: =AI26 -> -0.0045229903
B68: CapEx | F68: =F28 -> 298 | G68: =G28 -> 183 | H68: =H28 -> 222 | I68: =I28 -> 273 | J68: =J28 -> 361 | K68: =K28 -> 433 | L68: =L28 -> 530 | M68: =M28 -> 509 | ... AI68: =AI28 -> 5115
B69: % of revenue | F69: =F29 -> 0.052640876 | G69: =G29 -> 0.028123559 | H69: =H29 -> 0.0312544 | I69: =I29 -> 0.035718959 | J69: =J29 -> 0.04355695 | K69: =K29 -> 0.064588305 | L69: =L29 -> 0.089360985 | M69: =M29 -> 0.084118328 | ... AI69: =AI29 -> 0.015999374
B71: Change in NWC | F71: =F31 -> 887 | G71: =G31 -> 249 | H71: =H31 -> 192 | I71: =I31 -> 390 | J71: =J31 -> 389 | K71: =K31 -> 382 | L71: =L31 -> 417 | M71: =M31 -> -10 | ... AI71: =AI31 -> 26215
B72: % of revenue | F72: =F32 -> 0.1566861 | G72: =G32 -> 0.038266482 | H72: =H32 -> 0.027030832 | I72: =I32 -> 0.051027084 | J72: =J32 -> 0.046935328 | K72: =K32 -> 0.056980907 | L72: =L32 -> 0.070308548 | M72: =M32 -> -0.0016526194 | ... AI72: =AI32 -> 0.081998749
B74: Unlevered FCF | X74: =X63+X65-X68-X71 -> 23180.909 | Y74: =Y63+Y65-Y68-Y71 -> 27558.675 | Z74: =Z63+Z65-Z68-Z71 -> 26873.158 | AA74: =AA63+AA65-AA68-AA71 -> 27333.143 | AB74: =AB63+AB65-AB68-AB71 -> 26212.755 | AC74: =AC63+AC65-AC68-AC71 -> 25160.49 | AD74: =AD63+AD65-AD68-AD71 -> 24829.644 | AE74: =AE63+AE65-AE68-AE71 -> 21187.654 | ... AI74: =AI63+AI65-AI68-AI71 -> 127713.5
B75: Present value of Unlevered FCF | X75: =X74/(1+$D$42)^X78 -> 21216.457 | Y75: =Y74/(1+$D$42)^Y78 -> 25277.148 | Z75: =Z74/(1+$D$42)^Z78 -> 24699.799 | AA75: =AA74/(1+$D$42)^AA78 -> 25173.721 | AB75: =AB74/(1+$D$42)^AB78 -> 24189.805 | AC75: =AC74/(1+$D$42)^AC78 -> 23263.757 | AD75: =AD74/(1+$D$42)^AD78 -> 23001.282 | AE75: =AE74/(1+$D$42)^AE78 -> 19663.708 | ... AI75: =AI74/(1+$D$42)^AI78 -> 119353.4
B77: Period | X77: 1 | Y77: =X77 + 0.25 -> 1.25 | Z77: =Y77 + 0.25 -> 1.5 | AA77: =Z77 + 0.25 -> 1.75 | AB77: =AA77 + 0.25 -> 2 | AC77: =AB77 + 0.25 -> 2.25 | AD77: =AC77 + 0.25 -> 2.5 | AE77: =AD77 + 0.25 -> 2.75 | AF77: =AE77 + 0.25 -> 3 | ... AI77: =AH77 + 0.25 -> 3.75
B78: Discount factor | X78: =1 / (1 + $D$42) ^ X77 -> 0.90698113 | Y78: =1 / (1 + $D$42) ^ Y77 -> 0.88511116 | Z78: =1 / (1 + $D$42) ^ Z77 -> 0.86376853 | AA78: =1 / (1 + $D$42) ^ AA77 -> 0.84294054 | AB78: =1 / (1 + $D$42) ^ AB77 -> 0.82261477 | AC78: =1 / (1 + $D$42) ^ AC77 -> 0.80277912 | AD78: =1 / (1 + $D$42) ^ AD77 -> 0.78342176 | AE78: =1 / (1 + $D$42) ^ AE77 -> 0.76453117 | ... AI78: =1 / (1 + $D$42) ^ AI77 -> 0.69341534
B80: Terminal Value | E80: =(AI74*(1+D43))/(D42-D43) -> 1956570.2
B81: PV of Terminal Value | E81: =E80/(1+D42)^AI77 -> 1356715.8
B82: Enterprise Value | E82: =E81+SUM(X75:AI75) -> 1794732.7
B83: (+) Cash | E83: ='Balance Sheet'!S11+'Balance Sheet'!T11 -> 26873
B84: (-) Debt | E84: =Debt!U8 -> 8466
B85: Equity Value | E85: =E82+E83-E84 -> 1813139.7
B87: Diluted Shares | E87: 2453
B88: Implied Stock Price | E88: =E85/E87 -> 739.15195
